Workbook
Name Conv: _xlfn.LAMBDA(_xlpm.deg,_xlpm.min,_xlpm.sec,_xlpm.dir,IF(OR(_xlpm.dir="S",_xlpm.dir="W"), -(_xlpm.deg + _xlpm.min/60 + _xlpm.sec/3600), _xlpm.deg + _xlpm.min/60 + _xlpm.sec/3600 ) )

Sheet Modern
A1: Country | B1: Area | C1: AreaRank | D1: Pop | E1: PopRank | F1: Independence | G1: Year | H1: YearRank | I1: Capital | J1: CapPop | K1: CapPopRank | L1: Density | M1: DensRank | N1: CityShare | O1: ShareRank | P1: Continent | Q1: Begin | R1: End | S1: NameChanges
A2: Singapore | B2: 284 | C2: =RANK(B2,B$2:B$197) -> 176 | D2: 6158000 | E2: =RANK(D2,D$2:D$197) -> 115 | F2: 1965-08-09 | G2: 1965 | H2: =RANK(G2,G$2:G$197) -> 73 | I2: Singapore | J2: 6158000 | K2: =RANK(J2,J$2:J$197) -> 20 | L2: =D2/B2 -> 21683.099 | M2: =RANK(L2,L$2:L$197) -> 2 | N2: =J2/D2 -> 1 | O2: =RANK(N2,N$2:N$197) -> 1 | P2: Asia | Q2: 1965 | R2: 2026
A3: Vatican City | B3: 0.19 | C3: =RANK(B3,B$2:B$197) -> 196 | D3: 882 | E3: =RANK(D3,D$2:D$197) -> 196 | F3: 1929-02-11 | G3: 1929 | H3: =RANK(G3,G$2:G$197) -> 137 | I3: Vatican City | J3: 882 | K3: =RANK(J3,J$2:J$197) -> 194 | L3: =D3/B3 -> 4642.1053 | M3: =RANK(L3,L$2:L$197) -> 6 | N3: =J3/D3 -> 1 | O3: =RANK(N3,N$2:N$197) -> 1 | P3: Europe | Q3: 1929 | R3: 2026
A4: Bahamas | B4: 5382 | C4: =RANK(B4,B$2:B$197) -> 156 | D4: 413400 | E4: =RANK(D4,D$2:D$197) -> 172 | F4: 1973-07-10 | G4: 1973 | H4: =RANK(G4,G$2:G$197) -> 55 | I4: Nassau | J4: 296522 | K4: =RANK(J4,J$2:J$197) -> 141 | L4: =D4/B4 -> 76.811594 | M4: =RANK(L4,L$2:L$197) -> 154 | N4: =J4/D4 -> 0.71727625 | O4: =RANK(N4,N$2:N$197) -> 3 | P4: North America | Q4: 1973 | R4: 2026
A5: Djibouti | B5: 8958 | C5: =RANK(B5,B$2:B$197) -> 147 | D5: 1088000 | E5: =RANK(D5,D$2:D$197) -> 158 | F5: 1977-06-27 | G5: 1977 | H5: =RANK(G5,G$2:G$197) -> 43 | I5: Djibouti City | J5: 776966 | K5: =RANK(J5,J$2:J$197) -> 104 | L5: =D5/B5 -> 121.45568 | M5: =RANK(L5,L$2:L$197) -> 138 | N5: =J5/D5 -> 0.71412316 | O5: =RANK(N5,N$2:N$197) -> 4 | P5: Africa | Q5: 1977 | R5: 2026
A6: Tuvalu | B6: 10.14 | C6: =RANK(B6,B$2:B$197) -> 193 | D6: 9700 | E6: =RANK(D6,D$2:D$197) -> 195 | F6: 1978-10-01 | G6: 1978 | H6: =RANK(G6,G$2:G$197) -> 40 | I6: Funafuti | J6: 6602 | K6: =RANK(J6,J$2:J$197) -> 188 | L6: =D6/B6 -> 956.6075 | M6: =RANK(L6,L$2:L$197) -> 23 | N6: =J6/D6 -> 0.68061856 | O6: =RANK(N6,N$2:N$197) -> 5 | P6: Oceania | Q6: 1978 | R6: 2026
A7: Kuwait | B7: 6880 | C7: =RANK(B7,B$2:B$197) -> 153 | D7: 5098000 | E7: =RANK(D7,D$2:D$197) -> 126 | F7: 1961-06-19 | G7: 1961 | H7: =RANK(G7,G$2:G$197) -> 90 | I7: Kuwait City | J7: 3405000 | K7: =RANK(J7,J$2:J$197) -> 31 | L7: =D7/B7 -> 740.98837 | M7: =RANK(L7,L$2:L$197) -> 33 | N7: =J7/D7 -> 0.66790898 | O7: =RANK(N7,N$2:N$197) -> 6 | P7: Asia | Q7: 1961 | R7: 2026
A8: Marshall Islands | B8: 70 | C8: =RANK(B8,B$2:B$197) -> 190 | D8: 38900 | E8: =RANK(D8,D$2:D$197) -> 190 | F8: 1979-05-01 | G8: 1979 | H8: =RANK(G8,G$2:G$197) -> 35 | I8: Majuro | J8: 23156 | K8: =RANK(J8,J$2:J$197) -> 180 | L8: =D8/B8 -> 555.71429 | M8: =RANK(L8,L$2:L$197) -> 48 | N8: =J8/D8 -> 0.59526992 | O8: =RANK(N8,N$2:N$197) -> 7 | P8: Oceania | Q8: 1979 | R8: 2026
A9: Kiribati | B9: 313 | C9: =RANK(B9,B$2:B$197) -> 173 | D9: 128800 | E9: =RANK(D9,D$2:D$197) -> 179 | F9: 1979-07-12 | G9: 1979 | H9: =RANK(G9,G$2:G$197) -> 35 | I9: Tarawa | J9: 70480 | K9: =RANK(J9,J$2:J$197) -> 170 | L9: =D9/B9 -> 411.5016 | M9: =RANK(L9,L$2:L$197) -> 57 | N9: =J9/D9 -> 0.54720497 | O9: =RANK(N9,N$2:N$197) -> 8 | P9: Oceania | Q9: 1979 | R9: 2026
A10: Mongolia | B10: 603908 | C10: =RANK(B10,B$2:B$197) -> 18 | D10: 3569000 | E10: =RANK(D10,D$2:D$197) -> 131 | F10: 1924-11-26 | G10: 1924 | H10: =RANK(G10,G$2:G$197) -> 138 | I10: Ulaanbaatar | J10: 1672627 | K10: =RANK(J10,J$2:J$197) -> 65 | L10: =D10/B10 -> 5.9098406 | M10: =RANK(L10,L$2:L$197) -> 196 | N10: =J10/D10 -> 0.46865424 | O10: =RANK(N10,N$2:N$197) -> 9 | P10: Asia | Q10: 1924 | R10: 2026
A11: Bahrain | B11: 304 | C11: =RANK(B11,B$2:B$197) -> 174 | D11: 1628000 | E11: =RANK(D11,D$2:D$197) -> 150 | F11: 1971-08-14 | G11: 1971 | H11: =RANK(G11,G$2:G$197) -> 57 | I11: Manama | J11: 743066 | K11: =RANK(J11,J$2:J$197) -> 109 | L11: =D11/B11 -> 5355.2632 | M11: =RANK(L11,L$2:L$197) -> 3 | N11: =J11/D11 -> 0.45642875 | O11: =RANK(N11,N$2:N$197) -> 10 | P11: Asia | Q11: 1971 | R11: 2026
A12: Barbados | B12: 167 | C12: =RANK(B12,B$2:B$197) -> 184 | D12: 264300 | E12: =RANK(D12,D$2:D$197) -> 175 | F12: 1966-11-30 | G12: 1966 | H12: =RANK(G12,G$2:G$197) -> 68 | I12: Bridgetown | J12: 110000 | K12: =RANK(J12,J$2:J$197) -> 163 | L12: =D12/B12 -> 1582.6347 | M12: =RANK(L12,L$2:L$197) -> 10 | N12: =J12/D12 -> 0.41619372 | O12: =RANK(N12,N$2:N$197) -> 11 | P12: North America | Q12: 1966 | R12: 2026
A13: Jordan | B13: 34284 | C13: =RANK(B13,B$2:B$197) -> 110 | D13: 11845000 | E13: =RANK(D13,D$2:D$197) -> 85 | F13: 1946-05-25 | G13: 1946 | H13: =RANK(G13,G$2:G$197) -> 127 | I13: Amman | J13: 4920100 | K13: =RANK(J13,J$2:J$197) -> 24 | L13: =D13/B13 -> 345.49644 | M13: =RANK(L13,L$2:L$197) -> 69 | N13: =J13/D13 -> 0.41537358 | O13: =RANK(N13,N$2:N$197) -> 12 | P13: Asia | Q13: 1946 | R13: 2026
... A89: Comoros | B89: 719 | C89: =RANK(B89,B$2:B$197) -> 171 | D89: 877400 | E89: =RANK(D89,D$2:D$197) -> 160 | F89: 1975-07-06 | G89: 1975 | H89: =RANK(G89,G$2:G$197) -> 46 | I89: Moroni | J89: 111326 | K89: =RANK(J89,J$2:J$197) -> 162 | L89: =D89/B89 -> 1220.306 | M89: =RANK(L89,L$2:L$197) -> 18 | N89: =J89/D89 -> 0.1268817 | O89: =RANK(N89,N$2:N$197) -> 88 | P89: Africa | Q89: 1975 | R89: 2026
A90: Thailand | B90: 198124 | C90: =RANK(B90,B$2:B$197) -> 49 | D90: 66220000 | E90: =RANK(D90,D$2:D$197) -> 23 | F90: 1932-06-24 | G90: 1932 | H90: =RANK(G90,G$2:G$197) -> 133 | I90: Bangkok | J90: 8305218 | K90: =RANK(J90,J$2:J$197) -> 15 | L90: =D90/B90 -> 334.23513 | M90: =RANK(L90,L$2:L$197) -> 70 | N90: =J90/D90 -> 0.12541857 | O90: =RANK(N90,N$2:N$197) -> 89 | P90: Asia | Q90: 1932 | R90: 2026 | S90: Changed from Siam in 1939
A91: Rwanda | B91: 10169 | C91: =RANK(B91,B$2:B$197) -> 145 | D91: 14105000 | E91: =RANK(D91,D$2:D$197) -> 78 | F91: 1962-07-01 | G91: 1962 | H91: =RANK(G91,G$2:G$197) -> 84 | I91: Kigali | J91: 1745555 | K91: =RANK(J91,J$2:J$197) -> 61 | L91: =D91/B91 -> 1387.0587 | M91: =RANK(L91,L$2:L$197) -> 14 | N91: =J91/D91 -> 0.12375434 | O91: =RANK(N91,N$2:N$197) -> 90 | P91: Africa | Q91: 1962 | R91: 2026
A92: Central African Republic | B92: 240324 | C92: =RANK(B92,B$2:B$197) -> 43 | D92: 6602000 | E92: =RANK(D92,D$2:D$197) -> 109 | F92: 1958-12-01 | G92: 1958 | H92: =RANK(G92,G$2:G$197) -> 107 | I92: Bangui | J92: 812407 | K92: =RANK(J92,J$2:J$197) -> 102 | L92: =D92/B92 -> 27.471247 | M92: =RANK(L92,L$2:L$197) -> 183 | N92: =J92/D92 -> 0.12305468 | O92: =RANK(N92,N$2:N$197) -> 91 | P92: Africa | Q92: 1958 | R92: 2026
A93: Finland | B93: 130692 | C93: =RANK(B93,B$2:B$197) -> 66 | D93: 5642000 | E93: =RANK(D93,D$2:D$197) -> 119 | F93: 1917-12-06 | G93: 1917 | H93: =RANK(G93,G$2:G$197) -> 143 | I93: Helsinki | J93: 689758 | K93: =RANK(J93,J$2:J$197) -> 115 | L93: =D93/B93 -> 43.170202 | M93: =RANK(L93,L$2:L$197) -> 176 | N93: =J93/D93 -> 0.12225417 | O93: =RANK(N93,N$2:N$197) -> 92 | P93: Europe | Q93: 1917 | R93: 2026
A94: San Marino | B94: 24 | C94: =RANK(B94,B$2:B$197) -> 192 | D94: 34100 | E94: =RANK(D94,D$2:D$197) -> 192 | F94: 1291-01-01 | G94: 1291 | H94: =RANK(G94,G$2:G$197) -> 189 | I94: San Marino | J94: 4118 | K94: =RANK(J94,J$2:J$197) -> 191 | L94: =D94/B94 -> 1420.8333 | M94: =RANK(L94,L$2:L$197) -> 12 | N94: =J94/D94 -> 0.12076246 | O94: =RANK(N94,N$2:N$197) -> 93 | P94: Europe | Q94: 1291 | R94: 2026
A95: North Korea | B95: 47573 | C95: =RANK(B95,B$2:B$197) -> 97 | D95: 26403000 | E95: =RANK(D95,D$2:D$197) -> 56 | F95: 1948-07-10 | G95: 1948 | H95: =RANK(G95,G$2:G$197) -> 120 | I95: Pyongyang | J95: 3157538 | K95: =RANK(J95,J$2:J$197) -> 35 | L95: =D95/B95 -> 554.99968 | M95: =RANK(L95,L$2:L$197) -> 49 | N95: =J95/D95 -> 0.11959012 | O95: =RANK(N95,N$2:N$197) -> 94 | P95: Asia | Q95: 1948 | R95: 2026
A96: Syria | B96: 71498 | C96: =RANK(B96,B$2:B$197) -> 87 | D96: 23607000 | E96: =RANK(D96,D$2:D$197) -> 59 | F96: 1963-03-08 | G96: 1963 | H96: =RANK(G96,G$2:G$197) -> 81 | I96: Damascus | J96: 2799960 | K96: =RANK(J96,J$2:J$197) -> 39 | L96: =D96/B96 -> 330.17707 | M96: =RANK(L96,L$2:L$197) -> 71 | N96: =J96/D96 -> 0.11860719 | O96: =RANK(N96,N$2:N$197) -> 95 | P96: Asia | Q96: 1963 | R96: 2026
A97: Tajikistan | B97: 54595 | C97: =RANK(B97,B$2:B$197) -> 94 | D97: 10576000 | E97: =RANK(D97,D$2:D$197) -> 92 | F97: 1991-09-09 | G97: 1991 | H97: =RANK(G97,G$2:G$197) -> 8 | I97: Dushanbe | J97: 1228400 | K97: =RANK(J97,J$2:J$197) -> 79 | L97: =D97/B97 -> 193.71737 | M97: =RANK(L97,L$2:L$197) -> 110 | N97: =J97/D97 -> 0.11614977 | O97: =RANK(N97,N$2:N$197) -> 96 | P97: Asia | Q97: 1991 | R97: 2026
A98: Japan | B98: 145937 | C98: =RANK(B98,B$2:B$197) -> 62 | D98: 123105000 | E98: =RANK(D98,D$2:D$197) -> 11 | F98: 710-01-01 | G98: 710 | H98: =RANK(G98,G$2:G$197) -> 194 | I98: Tokyo | J98: 14254039 | K98: =RANK(J98,J$2:J$197) -> 3 | L98: =D98/B98 -> 843.54893 | M98: =RANK(L98,L$2:L$197) -> 27 | N98: =J98/D98 -> 0.11578765 | O98: =RANK(N98,N$2:N$197) -> 97 | P98: Asia | Q98: 710 | R98: 2026
A99: Saint Vincent and the Grenadines | B99: 150 | C99: =RANK(B99,B$2:B$197) -> 185 | D99: 111600 | E99: =RANK(D99,D$2:D$197) -> 181 | F99: 1979-10-27 | G99: 1979 | H99: =RANK(G99,G$2:G$197) -> 35 | I99: Kingstown | J99: 12909 | K99: =RANK(J99,J$2:J$197) -> 186 | L99: =D99/B99 -> 744 | M99: =RANK(L99,L$2:L$197) -> 31 | N99: =J99/D99 -> 0.11567204 | O99: =RANK(N99,N$2:N$197) -> 98 | P99: North America | Q99: 1979 | R99: 2026
A100: Guinea | B100: 94926 | C100: =RANK(B100,B$2:B$197) -> 77 | D100: 14364000 | E100: =RANK(D100,D$2:D$197) -> 76 | F100: 1958-10-02 | G100: 1958 | H100: =RANK(G100,G$2:G$197) -> 107 | I100: Conakry | J100: 1660973 | K100: =RANK(J100,J$2:J$197) -> 66 | L100: =D100/B100 -> 151.31787 | M100: =RANK(L100,L$2:L$197) -> 125 | N100: =J100/D100 -> 0.11563443 | O100: =RANK(N100,N$2:N$197) -> 99 | P100: Africa | Q100: 1958 | R100: 2026
A101: Saint Lucia | B101: 242 | C101: =RANK(B101,B$2:B$197) -> 179 | D101: 174800 | E101: =RANK(D101,D$2:D$197) -> 178 | F101: 1979-02-22 | G101: 1979 | H101: =RANK(G101,G$2:G$197) -> 35 | I101: Castries | J101: 20000 | K101: =RANK(J101,J$2:J$197) -> 183 | L101: =D101/B101 -> 722.31405 | M101: =RANK(L101,L$2:L$197) -> 34 | N101: =J101/D101 -> 0.11441648 | O101: =RANK(N101,N$2:N$197) -> 100 | P101: North America | Q101: 1979 | R101: 2026
A102: Kenya | B102: 224961 | C102: =RANK(B102,B$2:B$197) -> 46 | D102: 53477000 | E102: =RANK(D102,D$2:D$197) -> 28 | F102: 1964-12-12 | G102: 1964 | H102: =RANK(G102,G$2:G$197) -> 77 | I102: Nairobi | J102: 6100000 | K102: =RANK(J102,J$2:J$197) -> 21 | L102: =D102/B102 -> 237.71676 | M102: =RANK(L102,L$2:L$197) -> 96 | N102: =J102/D102 -> 0.11406773 | O102: =RANK(N102,N$2:N$197) -> 101 | P102: Africa | Q102: 1964 | R102: 2026
... A113: Ecuador | B113: 99170 | C113: =RANK(B113,B$2:B$197) -> 76 | D113: 17573000 | E113: =RANK(D113,D$2:D$197) -> 72 | F113: 1830-05-13 | G113: 1830 | H113: =RANK(G113,G$2:G$197) -> 167 | I113: Quito | J113: 1763275 | K113: =RANK(J113,J$2:J$197) -> 59 | L113: =D113/B113 -> 177.20077 | M113: =RANK(L113,L$2:L$197) -> 119 | N113: =J113/D113 -> 0.10034001 | O113: =RANK(N113,N$2:N$197) -> 112 | P113: South America | Q113: 1830 | R113: 2026
A114: Burkina Faso | B114: 104543 | C114: =RANK(B114,B$2:B$197) -> 73 | D114: 24071000 | E114: =RANK(D114,D$2:D$197) -> 58 | F114: 1960-08-05 | G114: 1960 | H114: =RANK(G114,G$2:G$197) -> 92 | I114: Ouagadougou | J114: 2415266 | K114: =RANK(J114,J$2:J$197) -> 43 | L114: =D114/B114 -> 230.24975 | M114: =RANK(L114,L$2:L$197) -> 100 | N114: =J114/D114 -> 0.10033925 | O114: =RANK(N114,N$2:N$197) -> 113 | P114: Africa | Q114: 1960 | R114: 2026 | S114: Changed from Upper Volta 1984
A115: Botswana | B115: 220141 | C115: =RANK(B115,B$2:B$197) -> 47 | D115: 2475000 | E115: =RANK(D115,D$2:D$197) -> 141 | F115: 1966-09-30 | G115: 1966 | H115: =RANK(G115,G$2:G$197) -> 68 | I115: Gabarone | J115: 246325 | K115: =RANK(J115,J$2:J$197) -> 148 | L115: =D115/B115 -> 11.242794 | M115: =RANK(L115,L$2:L$197) -> 189 | N115: =J115/D115 -> 0.099525253 | O115: =RANK(N115,N$2:N$197) -> 114 | P115: Africa | Q115: 1966 | R115: 2026
A116: Romania | B116: 92046 | C116: =RANK(B116,B$2:B$197) -> 81 | D116: 19079000 | E116: =RANK(D116,D$2:D$197) -> 69 | F116: 1877-05-10 | G116: 1877 | H116: =RANK(G116,G$2:G$197) -> 153 | I116: Bucharest | J116: 1877155 | K116: =RANK(J116,J$2:J$197) -> 56 | L116: =D116/B116 -> 207.2768 | M116: =RANK(L116,L$2:L$197) -> 105 | N116: =J116/D116 -> 0.098388542 | O116: =RANK(N116,N$2:N$197) -> 115 | P116: Europe | Q116: 1877 | R116: 2026
A117: Egypt | B117: 384790 | C117: =RANK(B117,B$2:B$197) -> 29 | D117: 107838000 | E117: =RANK(D117,D$2:D$197) -> 15 | F117: 1922-02-28 | G117: 1922 | H117: =RANK(G117,G$2:G$197) -> 141 | I117: Cairo | J117: 10500000 | K117: =RANK(J117,J$2:J$197) -> 6 | L117: =D117/B117 -> 280.25157 | M117: =RANK(L117,L$2:L$197) -> 81 | N117: =J117/D117 -> 0.097368275 | O117: =RANK(N117,N$2:N$197) -> 116 | P117: Africa | Q117: 1922 | R117: 2026
A118: Haiti | B118: 10450 | C118: =RANK(B118,B$2:B$197) -> 144 | D118: 12562000 | E118: =RANK(D118,D$2:D$197) -> 81 | F118: 1825-04-17 | G118: 1825 | H118: =RANK(G118,G$2:G$197) -> 170 | I118: Port-au-Prince | J118: 1200000 | K118: =RANK(J118,J$2:J$197) -> 81 | L118: =D118/B118 -> 1202.1053 | M118: =RANK(L118,L$2:L$197) -> 19 | N118: =J118/D118 -> 0.09552619 | O118: =RANK(N118,N$2:N$197) -> 117 | P118: North America | Q118: 1825 | R118: 2026
A119: Sweden | B119: 172751 | C119: =RANK(B119,B$2:B$197) -> 56 | D119: 10577000 | E119: =RANK(D119,D$2:D$197) -> 91 | F119: 1523-06-06 | G119: 1523 | H119: =RANK(G119,G$2:G$197) -> 187 | I119: Stockholm | J119: 996264 | K119: =RANK(J119,J$2:J$197) -> 96 | L119: =D119/B119 -> 61.226853 | M119: =RANK(L119,L$2:L$197) -> 165 | N119: =J119/D119 -> 0.094191548 | O119: =RANK(N119,N$2:N$197) -> 118 | P119: Europe | Q119: 1523 | R119: 2026
A120: Venezuela | B120: 353841 | C120: =RANK(B120,B$2:B$197) -> 32 | D120: 34464000 | E120: =RANK(D120,D$2:D$197) -> 43 | F120: 1830-01-13 | G120: 1830 | H120: =RANK(G120,G$2:G$197) -> 167 | I120: Caracas | J120: 3242000 | K120: =RANK(J120,J$2:J$197) -> 33 | L120: =D120/B120 -> 97.39968 | M120: =RANK(L120,L$2:L$197) -> 146 | N120: =J120/D120 -> 0.094069174 | O120: =RANK(N120,N$2:N$197) -> 119 | P120: South America | Q120: 1830 | R120: 2026
A121: Panama | B121: 29037 | C121: =RANK(B121,B$2:B$197) -> 115 | D121: 4379000 | E121: =RANK(D121,D$2:D$197) -> 128 | F121: 1903-11-03 | G121: 1903 | H121: =RANK(G121,G$2:G$197) -> 148 | I121: Panama City | J121: 410354 | K121: =RANK(J121,J$2:J$197) -> 137 | L121: =D121/B121 -> 150.80759 | M121: =RANK(L121,L$2:L$197) -> 128 | N121: =J121/D121 -> 0.093709523 | O121: =RANK(N121,N$2:N$197) -> 120 | P121: North America | Q121: 1903 | R121: 2026
A122: Zimbabwe | B122: 150872 | C122: =RANK(B122,B$2:B$197) -> 60 | D122: 15952000 | E122: =RANK(D122,D$2:D$197) -> 74 | F122: 1965-11-11 | G122: 1965 | H122: =RANK(G122,G$2:G$197) -> 73 | I122: Harare | J122: 1491740 | K122: =RANK(J122,J$2:J$197) -> 69 | L122: =D122/B122 -> 105.73201 | M122: =RANK(L122,L$2:L$197) -> 145 | N122: =J122/D122 -> 0.093514293 | O122: =RANK(N122,N$2:N$197) -> 121 | P122: Africa | Q122: 1965 | R122: 2026 | S122: Changed from Rhodesia 1980
A123: Dominican Republic | B123: 18619 | C123: =RANK(B123,B$2:B$197) -> 128 | D123: 11074000 | E123: =RANK(D123,D$2:D$197) -> 87 | F123: 1844-02-27 | G123: 1844 | H123: =RANK(G123,G$2:G$197) -> 161 | I123: Santo Domingo | J123: 1029110 | K123: =RANK(J123,J$2:J$197) -> 92 | L123: =D123/B123 -> 594.76878 | M123: =RANK(L123,L$2:L$197) -> 46 | N123: =J123/D123 -> 0.092930287 | O123: =RANK(N123,N$2:N$197) -> 122 | P123: North America | Q123: 1844 | R123: 2026
A124: Algeria | B124: 919595 | C124: =RANK(B124,B$2:B$197) -> 10 | D124: 47803000 | E124: =RANK(D124,D$2:D$197) -> 32 | F124: 1962-07-05 | G124: 1962 | H124: =RANK(G124,G$2:G$197) -> 84 | I124: Algiers | J124: 4325000 | K124: =RANK(J124,J$2:J$197) -> 25 | L124: =D124/B124 -> 51.982666 | M124: =RANK(L124,L$2:L$197) -> 168 | N124: =J124/D124 -> 0.090475493 | O124: =RANK(N124,N$2:N$197) -> 123 | P124: Africa | Q124: 1962 | R124: 2026
A125: Russia | B125: 6592846 | C125: =RANK(B125,B$2:B$197) -> 1 | D125: 145335000 | E125: =RANK(D125,D$2:D$197) -> 9 | F125: 1991-12-12 | G125: 1991 | H125: =RANK(G125,G$2:G$197) -> 8 | I125: Moscow | J125: 13010012 | K125: =RANK(J125,J$2:J$197) -> 4 | L125: =D125/B125 -> 22.044349 | M125: =RANK(L125,L$2:L$197) -> 185 | N125: =J125/D125 -> 0.089517405 | O125: =RANK(N125,N$2:N$197) -> 124 | P125: Europe | Q125: 1991 | R125: 2026
A126: Slovakia | B126: 18932 | C126: =RANK(B126,B$2:B$197) -> 127 | D126: 5416000 | E126: =RANK(D126,D$2:D$197) -> 121 | F126: 1993-01-01 | G126: 1993 | H126: =RANK(G126,G$2:G$197) -> 3 | I126: Bratislava | J126: 479389 | K126: =RANK(J126,J$2:J$197) -> 131 | L126: =D126/B126 -> 286.07648 | M126: =RANK(L126,L$2:L$197) -> 79 | N126: =J126/D126 -> 0.088513479 | O126: =RANK(N126,N$2:N$197) -> 125 | P126: Europe | Q126: 1993 | R126: 2026
A127: Vietnam | B127: 127930 | C127: =RANK(B127,B$2:B$197) -> 68 | D127: 102028000 | E127: =RANK(D127,D$2:D$197) -> 16 | F127: 1976-07-02 | G127: 1976 | H127: =RANK(G127,G$2:G$197) -> 44 | I127: Hanoi | J127: 8807523 | K127: =RANK(J127,J$2:J$197) -> 13 | L127: =D127/B127 -> 797.5299 | M127: =RANK(L127,L$2:L$197) -> 29 | N127: =J127/D127 -> 0.086324568 | O127: =RANK(N127,N$2:N$197) -> 126 | P127: Asia | Q127: 1976 | R127: 2026
A128: Uzbekistan | B128: 173348 | C128: =RANK(B128,B$2:B$197) -> 55 | D128: 38192000 | E128: =RANK(D128,D$2:D$197) -> 38 | F128: 1991-09-01 | G128: 1991 | H128: =RANK(G128,G$2:G$197) -> 8 | I128: Tashkent | J128: 3164030 | K128: =RANK(J128,J$2:J$197) -> 34 | L128: =D128/B128 -> 220.31982 | M128: =RANK(L128,L$2:L$197) -> 103 | N128: =J128/D128 -> 0.08284536 | O128: =RANK(N128,N$2:N$197) -> 127 | P128: Asia | Q128: 1991 | R128: 2026
A129: El Salvador | B129: 8124 | C129: =RANK(B129,B$2:B$197) -> 150 | D129: 6366000 | E129: =RANK(D129,D$2:D$197) -> 113 | F129: 1841-01-30 | G129: 1841 | H129: =RANK(G129,G$2:G$197) -> 162 | I129: San Salvador | J129: 525990 | K129: =RANK(J129,J$2:J$197) -> 126 | L129: =D129/B129 -> 783.60414 | M129: =RANK(L129,L$2:L$197) -> 30 | N129: =J129/D129 -> 0.082624882 | O129: =RANK(N129,N$2:N$197) -> 128 | P129: South America | Q129: 1841 | R129: 2026
A130: Bosnia and Herzegovina | B130: 19772 | C130: =RANK(B130,B$2:B$197) -> 125 | D130: 3373000 | E130: =RANK(D130,D$2:D$197) -> 133 | F130: 1992-03-03 | G130: 1992 | H130: =RANK(G130,G$2:G$197) -> 5 | I130: Sarajevo | J130: 275524 | K130: =RANK(J130,J$2:J$197) -> 144 | L130: =D130/B130 -> 170.59478 | M130: =RANK(L130,L$2:L$197) -> 122 | N130: =J130/D130 -> 0.081685147 | O130: =RANK(N130,N$2:N$197) -> 129 | P130: Europe | Q130: 1992 | R130: 2026
A131: Kazakhstan | B131: 1052084 | C131: =RANK(B131,B$2:B$197) -> 8 | D131: 20462000 | E131: =RANK(D131,D$2:D$197) -> 65 | F131: 1991-12-10 | G131: 1991 | H131: =RANK(G131,G$2:G$197) -> 8 | I131: Astana | J131: 1622245 | K131: =RANK(J131,J$2:J$197) -> 67 | L131: =D131/B131 -> 19.449017 | M131: =RANK(L131,L$2:L$197) -> 186 | N131: =J131/D131 -> 0.079280862 | O131: =RANK(N131,N$2:N$197) -> 130 | P131: Asia | Q131: 1991 | R131: 2026
A132: Eswatini | B132: 6704 | C132: =RANK(B132,B$2:B$197) -> 154 | D132: 1217000 | E132: =RANK(D132,D$2:D$197) -> 157 | F132: 1968-09-06 | G132: 1968 | H132: =RANK(G132,G$2:G$197) -> 64 | I132: Mbabane | J132: 94874 | K132: =RANK(J132,J$2:J$197) -> 166 | L132: =D132/B132 -> 181.53341 | M132: =RANK(L132,L$2:L$197) -> 118 | N132: =J132/D132 -> 0.077957272 | O132: =RANK(N132,N$2:N$197) -> 131 | P132: Africa | Q132: 1968 | R132: 2026 | S132: Changed from Swaziland 2018
A133: Lebanon | B133: 4036 | C133: =RANK(B133,B$2:B$197) -> 163 | D133: 5688000 | E133: =RANK(D133,D$2:D$197) -> 117 | F133: 1943-11-22 | G133: 1943 | H133: =RANK(G133,G$2:G$197) -> 131 | I133: Beirut | J133: 433249 | K133: =RANK(J133,J$2:J$197) -> 135 | L133: =D133/B133 -> 1409.3162 | M133: =RANK(L133,L$2:L$197) -> 13 | N133: =J133/D133 -> 0.076168952 | O133: =RANK(N133,N$2:N$197) -> 132 | P133: Asia | Q133: 1943 | R133: 2026
A134: Yemen | B134: 175676 | C134: =RANK(B134,B$2:B$197) -> 54 | D134: 34355000 | E134: =RANK(D134,D$2:D$197) -> 45 | F134: 1990-05-22 | G134: 1990 | H134: =RANK(G134,G$2:G$197) -> 25 | I134: Sanaa | J134: 2545000 | K134: =RANK(J134,J$2:J$197) -> 41 | L134: =D134/B134 -> 195.55887 | M134: =RANK(L134,L$2:L$197) -> 108 | N134: =J134/D134 -> 0.074079464 | O134: =RANK(N134,N$2:N$197) -> 133 | P134: Asia | Q134: 1990 | R134: 2026
A135: Paraguay | B135: 157048 | C135: =RANK(B135,B$2:B$197) -> 59 | D135: 6247000 | E135: =RANK(D135,D$2:D$197) -> 114 | F135: 1811-05-14 | G135: 1811 | H135: =RANK(G135,G$2:G$197) -> 180 | I135: Asuncion | J135: 462241 | K135: =RANK(J135,J$2:J$197) -> 133 | L135: =D135/B135 -> 39.777648 | M135: =RANK(L135,L$2:L$197) -> 178 | N135: =J135/D135 -> 0.073994077 | O135: =RANK(N135,N$2:N$197) -> 134 | P135: South America | Q135: 1811 | R135: 2026
A136: Guatemala | B136: 42042 | C136: =RANK(B136,B$2:B$197) -> 104 | D136: 16865000 | E136: =RANK(D136,D$2:D$197) -> 73 | F136: 1839-04-17 | G136: 1839 | H136: =RANK(G136,G$2:G$197) -> 163 | I136: Guatemala City | J136: 1221739 | K136: =RANK(J136,J$2:J$197) -> 80 | L136: =D136/B136 -> 401.14647 | M136: =RANK(L136,L$2:L$197) -> 58 | N136: =J136/D136 -> 0.072442277 | O136: =RANK(N136,N$2:N$197) -> 135 | P136: North America | Q136: 1839 | R136: 2026
A137: Spain | B137: 195361 | C137: =RANK(B137,B$2:B$197) -> 50 | D137: 49270000 | E137: =RANK(D137,D$2:D$197) -> 30 | F137: 1516-03-14 | G137: 1516 | H137: =RANK(G137,G$2:G$197) -> 188 | I137: Madrid | J137: 3477497 | K137: =RANK(J137,J$2:J$197) -> 30 | L137: =D137/B137 -> 252.19977 | M137: =RANK(L137,L$2:L$197) -> 92 | N137: =J137/D137 -> 0.070580414 | O137: =RANK(N137,N$2:N$197) -> 136 | P137: Europe | Q137: 1516 | R137: 2026
A138: Ukraine | B138: 233032 | C138: =RANK(B138,B$2:B$197) -> 44 | D138: 42721000 | E138: =RANK(D138,D$2:D$197) -> 36 | F138: 1991-08-24 | G138: 1991 | H138: =RANK(G138,G$2:G$197) -> 8 | I138: Kyiv | J138: 2952301 | K138: =RANK(J138,J$2:J$197) -> 38 | L138: =D138/B138 -> 183.32675 | M138: =RANK(L138,L$2:L$197) -> 116 | N138: =J138/D138 -> 0.069106552 | O138: =RANK(N138,N$2:N$197) -> 137 | P138: Europe | Q138: 1991 | R138: 2026
A139: Greece | B139: 50984 | C139: =RANK(B139,B$2:B$197) -> 95 | D139: 9361000 | E139: =RANK(D139,D$2:D$197) -> 96 | F139: 1822-01-01 | G139: 1822 | H139: =RANK(G139,G$2:G$197) -> 174 | I139: Athens | J139: 643452 | K139: =RANK(J139,J$2:J$197) -> 119 | L139: =D139/B139 -> 183.60662 | M139: =RANK(L139,L$2:L$197) -> 115 | N139: =J139/D139 -> 0.068737528 | O139: =RANK(N139,N$2:N$197) -> 138 | P139: Europe | Q139: 1822 | R139: 2026
A140: Mexico | B140: 758449 | C140: =RANK(B140,B$2:B$197) -> 13 | D140: 134092000 | E140: =RANK(D140,D$2:D$197) -> 10 | F140: 1821-09-07 | G140: 1821 | H140: =RANK(G140,G$2:G$197) -> 176 | I140: Mexico City | J140: 9209944 | K140: =RANK(J140,J$2:J$197) -> 10 | L140: =D140/B140 -> 176.79765 | M140: =RANK(L140,L$2:L$197) -> 120 | N140: =J140/D140 -> 0.068683769 | O140: =RANK(N140,N$2:N$197) -> 139 | P140: North America | Q140: 1821 | R140: 2026
A141: Turkey | B141: 297146 | C141: =RANK(B141,B$2:B$197) -> 36 | D141: 86797000 | E141: =RANK(D141,D$2:D$197) -> 17 | F141: 1923-07-24 | G141: 1923 | H141: =RANK(G141,G$2:G$197) -> 139 | I141: Ankara | J141: 5910320 | K141: =RANK(J141,J$2:J$197) -> 22 | L141: =D141/B141 -> 292.1022 | M141: =RANK(L141,L$2:L$197) -> 78 | N141: =J141/D141 -> 0.068093598 | O141: =RANK(N141,N$2:N$197) -> 140 | P141: Asia | Q141: 1923 | R141: 2026
A142: Costa Rica | B142: 19730 | C142: =RANK(B142,B$2:B$197) -> 126 | D142: 5266000 | E142: =RANK(D142,D$2:D$197) -> 124 | F142: 1838-11-14 | G142: 1838 | H142: =RANK(G142,G$2:G$197) -> 164 | I142: San Jose | J142: 352381 | K142: =RANK(J142,J$2:J$197) -> 138 | L142: =D142/B142 -> 266.90319 | M142: =RANK(L142,L$2:L$197) -> 85 | N142: =J142/D142 -> 0.066916255 | O142: =RANK(N142,N$2:N$197) -> 141 | P142: South America | Q142: 1838 | R142: 2026
A143: Belize | B143: 8867 | C143: =RANK(B143,B$2:B$197) -> 148 | D143: 417300 | E143: =RANK(D143,D$2:D$197) -> 171 | F143: 1981-09-21 | G143: 1981 | H143: =RANK(G143,G$2:G$197) -> 31 | I143: Belmopan | J143: 27870 | K143: =RANK(J143,J$2:J$197) -> 178 | L143: =D143/B143 -> 47.062141 | M143: =RANK(L143,L$2:L$197) -> 173 | N143: =J143/D143 -> 0.066786485 | O143: =RANK(N143,N$2:N$197) -> 142 | P143: North America | Q143: 1981 | R143: 2026
A144: Senegal | B144: 75973 | C144: =RANK(B144,B$2:B$197) -> 86 | D144: 19179000 | E144: =RANK(D144,D$2:D$197) -> 68 | F144: 1960-06-20 | G144: 1960 | H144: =RANK(G144,G$2:G$197) -> 92 | I144: Dakar | J144: 1278469 | K144: =RANK(J144,J$2:J$197) -> 77 | L144: =D144/B144 -> 252.44495 | M144: =RANK(L144,L$2:L$197) -> 91 | N144: =J144/D144 -> 0.066659836 | O144: =RANK(N144,N$2:N$197) -> 143 | P144: Africa | Q144: 1960 | R144: 2026
... A174: Canada | B174: 3848758 | C174: =RANK(B174,B$2:B$197) -> 2 | D174: 42512000 | E174: =RANK(D174,D$2:D$197) -> 37 | F174: 1867-07-01 | G174: 1867 | H174: =RANK(G174,G$2:G$197) -> 155 | I174: Ottawa | J174: 1017449 | K174: =RANK(J174,J$2:J$197) -> 95 | L174: =D174/B174 -> 11.045641 | M174: =RANK(L174,L$2:L$197) -> 190 | N174: =J174/D174 -> 0.023933219 | O174: =RANK(N174,N$2:N$197) -> 173 | P174: North America | Q174: 1867 | R174: 2026
A175: Benin | B175: 44310 | C175: =RANK(B175,B$2:B$197) -> 100 | D175: 14054000 | E175: =RANK(D175,D$2:D$197) -> 79 | F175: 1960-08-01 | G175: 1960 | H175: =RANK(G175,G$2:G$197) -> 92 | I175: Porto Novo | J175: 264320 | K175: =RANK(J175,J$2:J$197) -> 145 | L175: =D175/B175 -> 317.17445 | M175: =RANK(L175,L$2:L$197) -> 72 | N175: =J175/D175 -> 0.018807457 | O175: =RANK(N175,N$2:N$197) -> 174 | P175: Africa | Q175: 1960 | R175: 2026 | S175: Changed from Dahomey 1975
A176: Palau | B176: 188 | C176: =RANK(B176,B$2:B$197) -> 180 | D176: 17600 | E176: =RANK(D176,D$2:D$197) -> 193 | F176: 1981-01-01 | G176: 1981 | H176: =RANK(G176,G$2:G$197) -> 31 | I176: Ngerulmud | J176: 318 | K176: =RANK(J176,J$2:J$197) -> 196 | L176: =D176/B176 -> 93.617021 | M176: =RANK(L176,L$2:L$197) -> 148 | N176: =J176/D176 -> 0.018068182 | O176: =RANK(N176,N$2:N$197) -> 175 | P176: Oceania | Q176: 1981 | R176: 2026
A177: Australia | B177: 2968401 | C177: =RANK(B177,B$2:B$197) -> 6 | D177: 27978000 | E177: =RANK(D177,D$2:D$197) -> 53 | F177: 1901-01-01 | G177: 1901 | H177: =RANK(G177,G$2:G$197) -> 150 | I177: Canberra | J177: 473855 | K177: =RANK(J177,J$2:J$197) -> 132 | L177: =D177/B177 -> 9.4252764 | M177: =RANK(L177,L$2:L$197) -> 195 | N177: =J177/D177 -> 0.0169367 | O177: =RANK(N177,N$2:N$197) -> 176 | P177: Oceania | Q177: 1901 | R177: 2026
A178: Philippines | B178: 134240 | C178: =RANK(B178,B$2:B$197) -> 64 | D178: 113863000 | E178: =RANK(D178,D$2:D$197) -> 12 | F178: 1946-07-04 | G178: 1946 | H178: =RANK(G178,G$2:G$197) -> 127 | I178: Manila | J178: 1902590 | K178: =RANK(J178,J$2:J$197) -> 55 | L178: =D178/B178 -> 848.20471 | M178: =RANK(L178,L$2:L$197) -> 26 | N178: =J178/D178 -> 0.016709467 | O178: =RANK(N178,N$2:N$197) -> 177 | P178: Asia | Q178: 1946 | R178: 2026
A179: Myanmar | B179: 261219 | C179: =RANK(B179,B$2:B$197) -> 39 | D179: 57940000 | E179: =RANK(D179,D$2:D$197) -> 26 | F179: 1948-01-04 | G179: 1948 | H179: =RANK(G179,G$2:G$197) -> 120 | I179: Nay Pyi Daw | J179: 924608 | K179: =RANK(J179,J$2:J$197) -> 99 | L179: =D179/B179 -> 221.80622 | M179: =RANK(L179,L$2:L$197) -> 101 | N179: =J179/D179 -> 0.015958026 | O179: =RANK(N179,N$2:N$197) -> 178 | P179: Asia | Q179: 1948 | R179: 2026 | S179: Changed from Burma 1989
A180: Belgium | B180: 11909 | C180: =RANK(B180,B$2:B$197) -> 137 | D180: 11863000 | E180: =RANK(D180,D$2:D$197) -> 84 | F180: 1803-10-04 | G180: 1830 | H180: =RANK(G180,G$2:G$197) -> 167 | I180: Brussels | J180: 188737 | K180: =RANK(J180,J$2:J$197) -> 152 | L180: =D180/B180 -> 996.13738 | M180: =RANK(L180,L$2:L$197) -> 22 | N180: =J180/D180 -> 0.015909719 | O180: =RANK(N180,N$2:N$197) -> 179 | P180: Europe | Q180: 1830 | R180: 2026
A181: China | B181: 3696116 | C181: =RANK(B181,B$2:B$197) -> 4 | D181: 1408671000 | E181: =RANK(D181,D$2:D$197) -> 1 | F181: -221-01-01 | G181: -221 | H181: =RANK(G181,G$2:G$197) -> 195 | I181: Beijing | J181: 21893095 | K181: =RANK(J181,J$2:J$197) -> 1 | L181: =D181/B181 -> 381.12197 | M181: =RANK(L181,L$2:L$197) -> 63 | N181: =J181/D181 -> 0.015541667 | O181: =RANK(N181,N$2:N$197) -> 180 | P181: Asia | Q181: -221 | R181: 2026
A182: Switzerland | B182: 15943 | C182: =RANK(B182,B$2:B$197) -> 131 | D182: 9127000 | E182: =RANK(D182,D$2:D$197) -> 99 | F182: 1648-10-24 | G182: 1648 | H182: =RANK(G182,G$2:G$197) -> 185 | I182: Bern | J182: 134794 | K182: =RANK(J182,J$2:J$197) -> 159 | L182: =D182/B182 -> 572.47695 | M182: =RANK(L182,L$2:L$197) -> 47 | N182: =J182/D182 -> 0.014768708 | O182: =RANK(N182,N$2:N$197) -> 181 | P182: Europe | Q182: 1648 | R182: 2026
A183: Brazil | B183: 3285890 | C183: =RANK(B183,B$2:B$197) -> 5 | D183: 206296000 | E183: =RANK(D183,D$2:D$197) -> 7 | F183: 1822-09-07 | G183: 1822 | H183: =RANK(G183,G$2:G$197) -> 174 | I183: Brasilia | J183: 2982818 | K183: =RANK(J183,J$2:J$197) -> 37 | L183: =D183/B183 -> 62.782382 | M183: =RANK(L183,L$2:L$197) -> 164 | N183: =J183/D183 -> 0.014458923 | O183: =RANK(N183,N$2:N$197) -> 182 | P183: South America | Q183: 1822 | R183: 2026
A184: Morocco | B184: 160835 | C184: =RANK(B184,B$2:B$197) -> 58 | D184: 37137000 | E184: =RANK(D184,D$2:D$197) -> 40 | F184: 1956-11-18 | G184: 1956 | H184: =RANK(G184,G$2:G$197) -> 111 | I184: Rabat | J184: 515619 | K184: =RANK(J184,J$2:J$197) -> 128 | L184: =D184/B184 -> 230.90123 | M184: =RANK(L184,L$2:L$197) -> 97 | N184: =J184/D184 -> 0.013884239 | O184: =RANK(N184,N$2:N$197) -> 183 | P184: Africa | Q184: 1956 | R184: 2026
A185: Ivory Coast | B185: 128364 | C185: =RANK(B185,B$2:B$197) -> 67 | D185: 33180000 | E185: =RANK(D185,D$2:D$197) -> 50 | F185: 1960-08-07 | G185: 1960 | H185: =RANK(G185,G$2:G$197) -> 92 | I185: Yamoussoukro | J185: 422072 | K185: =RANK(J185,J$2:J$197) -> 136 | L185: =D185/B185 -> 258.48369 | M185: =RANK(L185,L$2:L$197) -> 89 | N185: =J185/D185 -> 0.012720675 | O185: =RANK(N185,N$2:N$197) -> 184 | P185: Africa | Q185: 1960 | R185: 2026
A186: Gambia | B186: 4127 | C186: =RANK(B186,B$2:B$197) -> 162 | D186: 2461000 | E186: =RANK(D186,D$2:D$197) -> 142 | F186: 1965-02-18 | G186: 1965 | H186: =RANK(G186,G$2:G$197) -> 73 | I186: Banjul | J186: 31301 | K186: =RANK(J186,J$2:J$197) -> 176 | L186: =D186/B186 -> 596.31694 | M186: =RANK(L186,L$2:L$197) -> 45 | N186: =J186/D186 -> 0.012718813 | O186: =RANK(N186,N$2:N$197) -> 185 | P186: Africa | Q186: 1965 | R186: 2026
A187: South Africa | B187: 471358 | C187: =RANK(B187,B$2:B$197) -> 24 | D187: 63430000 | E187: =RANK(D187,D$2:D$197) -> 24 | F187: 1931-12-11 | G187: 1931 | H187: =RANK(G187,G$2:G$197) -> 136 | I187: Pretoria | J187: 741651 | K187: =RANK(J187,J$2:J$197) -> 110 | L187: =D187/B187 -> 134.56863 | M187: =RANK(L187,L$2:L$197) -> 135 | N187: =J187/D187 -> 0.011692433 | O187: =RANK(N187,N$2:N$197) -> 186 | P187: Africa | Q187: 1931 | R187: 2026
A188: Tanzania | B188: 365059 | C188: =RANK(B188,B$2:B$197) -> 30 | D188: 67529000 | E188: =RANK(D188,D$2:D$197) -> 21 | F188: 1964-04-26 | G188: 1964 | H188: =RANK(G188,G$2:G$197) -> 77 | I188: Dodoma | J188: 765179 | K188: =RANK(J188,J$2:J$197) -> 106 | L188: =D188/B188 -> 184.98106 | M188: =RANK(L188,L$2:L$197) -> 113 | N188: =J188/D188 -> 0.011331117 | O188: =RANK(N188,N$2:N$197) -> 187 | P188: Africa | Q188: 1964 | R188: 2026
A189: Burundi | B189: 10747 | C189: =RANK(B189,B$2:B$197) -> 143 | D189: 13605000 | E189: =RANK(D189,D$2:D$197) -> 80 | F189: 1962-07-01 | G189: 1962 | H189: =RANK(G189,G$2:G$197) -> 84 | I189: Gitega | J189: 135467 | K189: =RANK(J189,J$2:J$197) -> 158 | L189: =D189/B189 -> 1265.9347 | M189: =RANK(L189,L$2:L$197) -> 16 | N189: =J189/D189 -> 0.0099571481 | O189: =RANK(N189,N$2:N$197) -> 188 | P189: Africa | Q189: 1962 | R189: 2026
A190: Malta | B190: 122 | C190: =RANK(B190,B$2:B$197) -> 187 | D190: 569900 | E190: =RANK(D190,D$2:D$197) -> 167 | F190: 1964-09-21 | G190: 1964 | H190: =RANK(G190,G$2:G$197) -> 77 | I190: Valletta | J190: 5157 | K190: =RANK(J190,J$2:J$197) -> 190 | L190: =D190/B190 -> 4671.3115 | M190: =RANK(L190,L$2:L$197) -> 5 | N190: =J190/D190 -> 0.009048956 | O190: =RANK(N190,N$2:N$197) -> 189 | P190: Europe | Q190: 1964 | R190: 2026
A191: Ghana | B191: 92098 | C191: =RANK(B191,B$2:B$197) -> 80 | D191: 33512000 | E191: =RANK(D191,D$2:D$197) -> 48 | F191: 1957-03-06 | G191: 1957 | H191: =RANK(G191,G$2:G$197) -> 110 | I191: Accra | J191: 284124 | K191: =RANK(J191,J$2:J$197) -> 142 | L191: =D191/B191 -> 363.87327 | M191: =RANK(L191,L$2:L$197) -> 66 | N191: =J191/D191 -> 0.0084782764 | O191: =RANK(N191,N$2:N$197) -> 190 | P191: Africa | Q191: 1957 | R191: 2026
A192: Nigeria | B192: 356669 | C192: =RANK(B192,B$2:B$197) -> 31 | D192: 233560000 | E192: =RANK(D192,D$2:D$197) -> 6 | F192: 1960-10-01 | G192: 1960 | H192: =RANK(G192,G$2:G$197) -> 92 | I192: Abuja | J192: 1693400 | K192: =RANK(J192,J$2:J$197) -> 63 | L192: =D192/B192 -> 654.83684 | M192: =RANK(L192,L$2:L$197) -> 39 | N192: =J192/D192 -> 0.0072503853 | O192: =RANK(N192,N$2:N$197) -> 191 | P192: Africa | Q192: 1960 | R192: 2026
A193: Sri Lanka | B193: 25332 | C193: =RANK(B193,B$2:B$197) -> 120 | D193: 21751000 | E193: =RANK(D193,D$2:D$197) -> 61 | F193: 1948-02-04 | G193: 1948 | H193: =RANK(G193,G$2:G$197) -> 120 | I193: Sri Jayawardenepura Kotte | J193: 107925 | K193: =RANK(J193,J$2:J$197) -> 164 | L193: =D193/B193 -> 858.6373 | M193: =RANK(L193,L$2:L$197) -> 25 | N193: =J193/D193 -> 0.0049618408 | O193: =RANK(N193,N$2:N$197) -> 192 | P193: Asia | Q193: 1948 | R193: 2026 | S193: Changed from Ceylon 1972
A194: Pakistan | B194: 307374 | C194: =RANK(B194,B$2:B$197) -> 35 | D194: 255749000 | E194: =RANK(D194,D$2:D$197) -> 5 | F194: 1947-08-14 | G194: 1947 | H194: =RANK(G194,G$2:G$197) -> 126 | I194: Islamabad | J194: 1108872 | K194: =RANK(J194,J$2:J$197) -> 86 | L194: =D194/B194 -> 832.045 | M194: =RANK(L194,L$2:L$197) -> 28 | N194: =J194/D194 -> 0.0043357823 | O194: =RANK(N194,N$2:N$197) -> 193 | P194: Asia | Q194: 1947 | R194: 2026
A195: United States of America | B195: 3809525 | C195: =RANK(B195,B$2:B$197) -> 3 | D195: 343969000 | E195: =RANK(D195,D$2:D$197) -> 3 | F195: 1776-07-04 | G195: 1776 | H195: =RANK(G195,G$2:G$197) -> 183 | I195: Washington, D. C. | J195: 689545 | K195: =RANK(J195,J$2:J$197) -> 116 | L195: =D195/B195 -> 90.291834 | M195: =RANK(L195,L$2:L$197) -> 149 | N195: =J195/D195 -> 0.0020046719 | O195: =RANK(N195,N$2:N$197) -> 194 | P195: North America | Q195: 1776 | R195: 2026
A196: Equatorial Guinea | B196: 10831 | C196: =RANK(B196,B$2:B$197) -> 142 | D196: 1728000 | E196: =RANK(D196,D$2:D$197) -> 149 | F196: 1968-10-12 | G196: 1968 | H196: =RANK(G196,G$2:G$197) -> 64 | I196: Ciudad de la Paz | J196: 2000 | K196: =RANK(J196,J$2:J$197) -> 192 | L196: =D196/B196 -> 159.54206 | M196: =RANK(L196,L$2:L$197) -> 123 | N196: =J196/D196 -> 0.0011574074 | O196: =RANK(N196,N$2:N$197) -> 195 | P196: Africa | Q196: 1968 | R196: 2026
A197: India | B197: 1269219 | C197: =RANK(B197,B$2:B$197) -> 7 | D197: 1398885000 | E197: =RANK(D197,D$2:D$197) -> 2 | F197: 1950-01-26 | G197: 1950 | H197: =RANK(G197,G$2:G$197) -> 118 | I197: New Delhi | J197: 249998 | K197: =RANK(J197,J$2:J$197) -> 147 | L197: =D197/B197 -> 1102.162 | M197: =RANK(L197,L$2:L$197) -> 20 | N197: =J197/D197 -> 0.00017871233 | O197: =RANK(N197,N$2:N$197) -> 196 | P197: Asia | Q197: 1950 | R197: 2026

Sheet Sovereignty
A1: Polity | B1: Name | C1: Begin | D1: End | E1: Color | F1: Type | G1: Parent | H1: Continent | I1: Predecessor | J1: Country | K1: Filter | L1: Checked | M1: LegacyName | N1: LegacyCaps | O1: Sort | P1: Year => | Q1: =S509 -> 20260101
A2: DJI_1977 | B2: Djibouti | C2: 19770627 | D2: 20261231 | E2: #e41a1c | F2: Sovereign | H2: Africa | I2: DJI_1967_FRA | J2: =IF( F2 = "Sovereign", "x", "" ) -> x | K2: =( $C2<=$Q$1 )*( $D2 > $Q$1 ) * 1 -> 1 | L2: x | O2: 1
A3: DJI_1862_FRA | B3: Djibouti | C3: 18620311 | D3: 19770627 | E3: #BFE6FF | F3: Dependent | G3: France | H3: Africa | I3: NA | K3: =( $C3<=$Q$1 )*( $D3 > $Q$1 ) * 1 -> 0 | L3: x | O3: 2
A4: SOM_1960 | B4: Somalia | C4: 19600626 | D4: 20261231 | E4: #377eb8 | F4: Sovereign | H4: Africa | I4: SOM_1950_ITA/SOL_1884_UK | J4: =IF( F4 = "Sovereign", "x", "" ) -> x | K4: =( $C4<=$Q$1 )*( $D4 > $Q$1 ) * 1 -> 1 | L4: x | M4: Federal Republic of Somalia | N4: Mogadishu | O4: 3
A5: SOL_1884_UK | B5: British Somaliland | C5: 18840101 | D5: 19600626 | E5: #FFEEBA | F5: Dependent | G5: United Kingdom | H5: Africa | I5: NA | J5: =IF( F5 = "Sovereign", "x", "" ) | K5: =( $C5<=$Q$1 )*( $D5 > $Q$1 ) * 1 -> 0 | L5: x | M5: Somaliland Protectorate | N5: Berbera | O5: 4
A6: SOM_1950_ITA | B6: Somaliland | C6: 19500401 | D6: 19600701 | E6: #B9B9B9 | F6: Dependent | G6: Italy | H6: Africa | I6: SOM_1941_UK | K6: =( $C6<=$Q$1 )*( $D6 > $Q$1 ) * 1 -> 0 | L6: x | O6: 5
A7: SOM_1941_UK | B7: Somaliland | C7: 19410225 | D7: 19500401 | E7: #FFEEBA | F7: Dependent | G7: United Kingdom | H7: Africa | I7: IEA_1936_ITA | J7: =IF( F7 = "Sovereign", "x", "" ) | K7: =( $C7<=$Q$1 )*( $D7 > $Q$1 ) * 1 -> 0 | L7: x | O7: 6
A8: IEA_1936_ITA | B8: Italian East Africa | C8: 19360509 | D8: 19411127 | E8: #B9B9B9 | F8: Dependent | G8: Italy | H8: Africa | I8: ERI_1882_ITA/ETH_1855/SOM_1889_ITA/SOL_1884_UK | J8: =IF( F8 = "Sovereign", "x", "" ) | K8: =( $C8<=$Q$1 )*( $D8 > $Q$1 ) * 1 -> 0 | L8: x | M8: Italian East Africa | N8: Addis Ababa | O8: 7
A9: SOM_1889_ITA | B9: Italian Somaliland | C9: 18890208 | D9: 19360601 | E9: #B9B9B9 | F9: Dependent | G9: Italy | H9: Africa | I9: NA | J9: =IF( F9 = "Sovereign", "x", "" ) | K9: =( $C9<=$Q$1 )*( $D9 > $Q$1 ) * 1 -> 0 | L9: x | M9: Italian Somaliland | N9: Mogadiscio | O9: 8
A10: ERI_1993 | B10: Eritrea | C10: 19930524 | D10: 20261231 | E10: #4daf4a | F10: Sovereign | H10: Africa | I10: ETH_1941 | J10: =IF( F10 = "Sovereign", "x", "" ) -> x | K10: =( $C10<=$Q$1 )*( $D10 > $Q$1 ) * 1 -> 1 | L10: x | M10: State of Eritrea | N10: Asmara | O10: 9
A11: ERI_1952 | B11: Eritrea | C11: 19520915 | D11: 19621114 | E11: #984ea3 | F11: Sovereign | H11: Africa | I11: ETH_1941 | J11: =IF( F11 = "Sovereign", "x", "" ) -> x | K11: =( $C11<=$Q$1 )*( $D11 > $Q$1 ) * 1 -> 0 | L11: x | M11: Province of Eritrea | N11: Asmara | O11: 10
A12: ERI_1941_UK | B12: Eritrea | C12: 19411127 | D12: 19520915 | E12: #FFEEBA | F12: Dependent | G12: United Kingdom | H12: Africa | I12: IEA_1936_ITA | J12: =IF( F12 = "Sovereign", "x", "" ) | K12: =( $C12<=$Q$1 )*( $D12 > $Q$1 ) * 1 -> 0 | L12: x | M12: British Military Administration in Eritrea | N12: Asmara | O12: 11
A13: ERI_1882_ITA | B13: Italian Eritrea | C13: 18820705 | D13: 19360601 | E13: #B9B9B9 | F13: Dependent | G13: Italy | H13: Africa | I13: ETH_1855 | J13: =IF( F13 = "Sovereign", "x", "" ) | K13: =( $C13<=$Q$1 )*( $D13 > $Q$1 ) * 1 -> 0 | L13: x | M13: Colony of Eritrea | N13: Asmara | O13: 12
A14: ETH_1941 | B14: Ethiopia | C14: 19411127 | D14: 20261231 | E14: #ff7f00 | F14: Sovereign | H14: Africa | I14: IEA_1936_ITA | J14: =IF( F14 = "Sovereign", "x", "" ) -> x | K14: =( $C14<=$Q$1 )*( $D14 > $Q$1 ) * 1 -> 1 | L14: x | M14: Federal Democratic Republic of Eritrea | N14: Addis Ababa | O14: 13
A15: ETH_1855 | B15: Ethiopia | C15: 18550211 | D15: 19360509 | E15: #ffff33 | F15: Sovereign | H15: Africa | I15: NA | J15: =IF( F15 = "Sovereign", "x", "" ) -> x | K15: =( $C15<=$Q$1 )*( $D15 > $Q$1 ) * 1 -> 0 | L15: x | M15: Ethiopian Empire | N15: Addis Ababa | O15: 14
A16: CON_1960 | B16: Republic of the Congo | C16: 19600815 | D16: 20261231 | E16: #a65628 | F16: Sovereign | H16: Africa | I16: CON_1958_FRA | J16: =IF( F16 = "Sovereign", "x", "" ) -> x | K16: =( $C16<=$Q$1 )*( $D16 > $Q$1 ) * 1 -> 1 | L16: x | M16: Republic of the Congo | N16: Brazzaville | O16: 15
A17: CON_1958_FRA | B17: Republic of the Congo | C17: 19581128 | D17: 19600815 | E17: #BFE6FF | F17: Dependent | G17: France | H17: Africa | I17: FEA_1910_FRA | J17: =IF( F17 = "Sovereign", "x", "" ) | K17: =( $C17<=$Q$1 )*( $D17 > $Q$1 ) * 1 -> 0 | L17: x | M17: Republic of the Congo | N17: Brazzaville | O17: 16
A18: FEA_1910_FRA | B18: French Equatorial Africa | C18: 19100115 | D18: 19581128 | E18: #BFE6FF | F18: Dependent | G18: France | H18: Africa | I18: CON_1882_FRA/GAB_1885_FRA/CAR_1903_FRA/CHD_1900_FRA | J18: =IF( F18 = "Sovereign", "x", "" ) | K18: =( $C18<=$Q$1 )*( $D18 > $Q$1 ) * 1 -> 0 | L18: x | M18: French Equatorial Africa | N18: Brazzaville | O18: 17
A19: CON_1882_FRA | B19: French Congo | C19: 18821130 | D19: 19100115 | E19: #BFE6FF | F19: Dependent | G19: France | H19: Africa | I19: NA | J19: =IF( F19 = "Sovereign", "x", "" ) | K19: =( $C19<=$Q$1 )*( $D19 > $Q$1 ) * 1 -> 0 | L19: x | M19: French Congo | N19: Brazzaville | O19: 18
A20: GAB_1960 | B20: Gabon | C20: 19600817 | D20: 20261231 | E20: #f781bf | F20: Sovereign | H20: Africa | I20: GAB_1958_FRA | J20: =IF( F20 = "Sovereign", "x", "" ) -> x | K20: =( $C20<=$Q$1 )*( $D20 > $Q$1 ) * 1 -> 1 | L20: x | M20: Republic of Gabon | N20: Libreville | O20: 19
A21: GAB_1958_FRA | B21: French Gabon | C21: 19581128 | D21: 19600817 | E21: #BFE6FF | F21: Dependent | G21: France | H21: Africa | I21: FEA_1910_FRA | J21: =IF( F21 = "Sovereign", "x", "" ) | K21: =( $C21<=$Q$1 )*( $D21 > $Q$1 ) * 1 -> 0 | L21: x | M21: Republic of Gabon | N21: Libreville | O21: 20
A22: GAB_1885_FRA | B22: French Gabon | C22: 18850101 | D22: 19100115 | E22: #BFE6FF | F22: Dependent | G22: France | H22: Africa | I22: NA | J22: =IF( F22 = "Sovereign", "x", "" ) | K22: =( $C22<=$Q$1 )*( $D22 > $Q$1 ) * 1 -> 0 | L22: x | M22: Colony of Gabon | N22: Libreville | O22: 21
A23: CAR_1960 | B23: Central African Republic | C23: 19600813 | D23: 20261231 | E23: #999999 | F23: Sovereign | H23: Africa | I23: CAR_1958_FRA | J23: =IF( F23 = "Sovereign", "x", "" ) -> x | K23: =( $C23<=$Q$1 )*( $D23 > $Q$1 ) * 1 -> 1 | L23: x | M23: Central African Republic | N23: Bangui | O23: 22
A24: CAR_1958_FRA | B24: Central African Republic | C24: 19581201 | D24: 19600813 | E24: #BFE6FF | F24: Dependent | G24: France | H24: Africa | I24: FEA_1910_FRA | J24: =IF( F24 = "Sovereign", "x", "" ) | K24: =( $C24<=$Q$1 )*( $D24 > $Q$1 ) * 1 -> 0 | L24: x | M24: Central African Republic | N24: Bangui | O24: 23
A25: CAR_1903_FRA | B25: Ubangi-Shari | C25: 19031229 | D25: 19100115 | E25: #BFE6FF | F25: Dependent | G25: France | H25: Africa | I25: NA | J25: =IF( F25 = "Sovereign", "x", "" ) | K25: =( $C25<=$Q$1 )*( $D25 > $Q$1 ) * 1 -> 0 | L25: x | M25: Colony of Ubangi-Shari | N25: Abiras | O25: 24
A26: CHD_1960 | B26: Chad | C26: 19600811 | D26: 20261231 | E26: #66c2a5 | F26: Sovereign | H26: Africa | I26: CHD_1900_FRA | J26: =IF( F26 = "Sovereign", "x", "" ) -> x | K26: =( $C26<=$Q$1 )*( $D26 > $Q$1 ) * 1 -> 1 | L26: x | N26: N'Djamena | O26: 25
A27: CHD_1900_FRA | B27: French Chad | C27: 19000905 | D27: 19100115 | E27: #BFE6FF | F27: Dependent | G27: France | H27: Africa | I27: NA | J27: =IF( F27 = "Sovereign", "x", "" ) | K27: =( $C27<=$Q$1 )*( $D27 > $Q$1 ) * 1 -> 0 | L27: x | O27: 26
A28: CPV_1975 | B28: Cape Verde | C28: 19750705 | D28: 20261231 | E28: #fc8d62 | F28: Sovereign | H28: Africa | I28: CPV_1462_POR | J28: =IF( F28 = "Sovereign", "x", "" ) -> x | K28: =( $C28<=$Q$1 )*( $D28 > $Q$1 ) * 1 -> 1 | L28: x | M28: Republic of Cabo Verde | N28: Praia | O28: 27
A29: CPV_1462_POR | B29: Cape Verde | C29: 14620101 | D29: 19750705 | E29: #C98DE2 | F29: Dependent | G29: Portugal | H29: Africa | I29: NA | J29: =IF( F29 = "Sovereign", "x", "" ) | K29: =( $C29<=$Q$1 )*( $D29 > $Q$1 ) * 1 -> 0 | L29: x | M29: Overseas Province of Cape Verde | N29: Praia | O29: 28
A30: MRT_1960 | B30: Mauritania | C30: 19601128 | D30: 20261231 | E30: #8da0cb | F30: Sovereign | H30: Africa | I30: MRT_1958_FRA | J30: =IF( F30 = "Sovereign", "x", "" ) -> x | K30: =( $C30<=$Q$1 )*( $D30 > $Q$1 ) * 1 -> 1 | M30: Islamic Republic of Mauritania | N30: Nuoakchott | O30: 29
A31: MRT_1958_FRA | B31: French Mauritania | C31: 19581128 | D31: 19601128 | E31: #BFE6FF | F31: Dependent | G31: France | H31: Africa | I31: FWA_1895_FRA | J31: =IF( F31 = "Sovereign", "x", "" ) | K31: =( $C31<=$Q$1 )*( $D31 > $Q$1 ) * 1 -> 0 | M31: Islamic Republic of Mauritania | N31: Nuoakchott | O31: 30
A32: FWA_1895_FRA | B32: French West Africa | C32: 18951027 | D32: 19581218 | E32: #BFE6FF | F32: Dependent | G32: France | H32: Africa | I32: GUI_1891_FRA/MAL_1890_FRA/IVC_1893_FRA | J32: =IF( F32 = "Sovereign", "x", "" ) | K32: =( $C32<=$Q$1 )*( $D32 > $Q$1 ) * 1 -> 0 | M32: French West Africa | N32: Saint Louis | O32: 31
A33: MLF_1960 | B33: Mali Federation | C33: 19600620 | D33: 19600820 | E33: #e78ac3 | F33: Sovereign | H33: Africa | I33: MAL_1958_FRA/SEN_1958_FRA | J33: =IF( F33 = "Sovereign", "x", "" ) -> x | K33: =( $C33<=$Q$1 )*( $D33 > $Q$1 ) * 1 -> 0 | M33: Mali Federation | N33: Dakar | O33: 32
A34: SEN_1960 | B34: Senegal | C34: 19600820 | D34: 20261231 | E34: #a6d854 | F34: Sovereign | H34: Africa | I34: MLF_1960 | J34: =IF( F34 = "Sovereign", "x", "" ) -> x | K34: =( $C34<=$Q$1 )*( $D34 > $Q$1 ) * 1 -> 1 | M34: Republic of Senegal | N34: Dakar | O34: 33
A35: SEN_1958_FRA | B35: French Senegal | C35: 19581125 | D35: 19600620 | E35: #BFE6FF | F35: Dependent | G35: France | H35: Africa | I35: FWA_1895_FRA | J35: =IF( F35 = "Sovereign", "x", "" ) | K35: =( $C35<=$Q$1 )*( $D35 > $Q$1 ) * 1 -> 0 | M35: Republic of Senegal | N35: Dakar | O35: 34
A36: GAM_1965 | B36: The Gambia | C36: 19650218 | D36: 20261231 | E36: #ffd92f | F36: Sovereign | H36: Africa | I36: GAM_1816_UK | J36: =IF( F36 = "Sovereign", "x", "" ) -> x | K36: =( $C36<=$Q$1 )*( $D36 > $Q$1 ) * 1 -> 1 | M36: Republic of the Gambia | N36: Banjul | O36: 35
A37: GAM_1816_UK | B37: The Gambia | C37: 18161017 | D37: 19650218 | E37: #FFEEBA | F37: Dependent | G37: United Kingdom | H37: Africa | I37: NA | J37: =IF( F37 = "Sovereign", "x", "" ) | K37: =( $C37<=$Q$1 )*( $D37 > $Q$1 ) * 1 -> 0 | M37: Gambia Colony and Protectorate | N37: Bathurst | O37: 36
A38: GUI_1958 | B38: Guinea | C38: 19581002 | D38: 20261231 | E38: #e5c494 | F38: Sovereign | H38: Africa | I38: FWA_1895_FRA | J38: =IF( F38 = "Sovereign", "x", "" ) -> x | K38: =( $C38<=$Q$1 )*( $D38 > $Q$1 ) * 1 -> 1 | M38: Republic of Guinea | N38: Conakry | O38: 37
A39: GUI_1891_FRA | B39: French Guinea | C39: 18910101 | D39: 18951027 | E39: #BFE6FF | F39: Dependent | G39: France | H39: Africa | I39: NA | J39: =IF( F39 = "Sovereign", "x", "" ) | K39: =( $C39<=$Q$1 )*( $D39 > $Q$1 ) * 1 -> 0 | M39: Republic of Guinea | N39: Conakry | O39: 38
A40: GBS_1974 | B40: Guinea-Bissau | C40: 19740910 | D40: 20261231 | E40: #e41a1c | F40: Sovereign | H40: Africa | I40: GBS_1879_POR | J40: =IF( F40 = "Sovereign", "x", "" ) -> x | K40: =( $C40<=$Q$1 )*( $D40 > $Q$1 ) * 1 -> 1 | M40: Republic of Guinea-Bissau | N40: Bissau | O40: 39
A41: GBS_1879_POR | B41: Portuguese Guinea | C41: 18790101 | D41: 19740910 | E41: #C98DE2 | F41: Dependent | G41: Portugal | H41: Africa | I41: NA | J41: =IF( F41 = "Sovereign", "x", "" ) | K41: =( $C41<=$Q$1 )*( $D41 > $Q$1 ) * 1 -> 0 | M41: Colony of Portuguese Guinea | N41: Bissau | O41: 40
A42: LIB_1847 | B42: Liberia | C42: 18470726 | D42: 20261231 | E42: #377eb8 | F42: Sovereign | H42: Africa | I42: LIB_1822_ACS | J42: =IF( F42 = "Sovereign", "x", "" ) -> x | K42: =( $C42<=$Q$1 )*( $D42 > $Q$1 ) * 1 -> 1 | M42: Republic of Liberia | N42: Monrovia | O42: 41
A43: LIB_1822_ACS | B43: Liberia | C43: 18220107 | D43: 18470726 | E43: #4daf4a | F43: Dependent | G43: American Colonization Society | H43: Africa | I43: NA | J43: =IF( F43 = "Sovereign", "x", "" ) | K43: =( $C43<=$Q$1 )*( $D43 > $Q$1 ) * 1 -> 0 | M43: Colony of Liberia | N43: Monrovia | O43: 42
A44: IVC_1960 | B44: Ivory Coast | C44: 19600807 | D44: 20261231 | E44: #984ea3 | F44: Sovereign | H44: Africa | I44: IVC_1958_FRA | J44: =IF( F44 = "Sovereign", "x", "" ) -> x | K44: =( $C44<=$Q$1 )*( $D44 > $Q$1 ) * 1 -> 1 | M44: Republic of Cote d'Ivoire | N44: Yamoussoukro | O44: 43
A45: IVC_1958_FRA | B45: Ivory Coast | C45: 19581204 | D45: 19600807 | E45: #BFE6FF | F45: Dependent | G45: France | H45: Africa | I45: IVC_1893_FRA | J45: =IF( F45 = "Sovereign", "x", "" ) | K45: =( $C45<=$Q$1 )*( $D45 > $Q$1 ) * 1 -> 0 | M45: Republic of Cote d'Ivoire | N45: Abidjan | O45: 44
A46: IVC_1893_FRA | B46: Ivory Coast | C46: 18930310 | D46: 19581204 | E46: #BFE6FF | F46: Dependent | G46: France | H46: Africa | I46: NA | J46: =IF( F46 = "Sovereign", "x", "" ) | K46: =( $C46<=$Q$1 )*( $D46 > $Q$1 ) * 1 -> 0 | M46: Colony of Ivory Coast | N46: Grand-Bassam | O46: 45
A47: GHA_1957 | B47: Ghana | C47: 19570306 | D47: 20261231 | E47: #ff7f00 | F47: Sovereign | H47: Africa | I47: GHA_1821_UK | J47: =IF( F47 = "Sovereign", "x", "" ) -> x | K47: =( $C47<=$Q$1 )*( $D47 > $Q$1 ) * 1 -> 1 | M47: Republic of Ghana | N47: Accra | O47: 46
A48: TOG_1960 | B48: Togo | C48: 19600427 | D48: 20261231 | E48: #ffff33 | F48: Sovereign | H48: Africa | I48: TOG_1956_FRA | J48: =IF( F48 = "Sovereign", "x", "" ) -> x | K48: =( $C48<=$Q$1 )*( $D48 > $Q$1 ) * 1 -> 1 | M48: Togolese Republic | N48: Lome | O48: 47
A49: TOG_1956_FRA | B49: Togo | C49: 19560910 | D49: 19600427 | E49: #BFE6FF | F49: Dependent | G49: France | H49: Africa | I49: TOG_1916_FRA | J49: =IF( F49 = "Sovereign", "x", "" ) | K49: =( $C49<=$Q$1 )*( $D49 > $Q$1 ) * 1 -> 0 | M49: Republic of Togo | N49: Lome | O49: 48
A50: TOG_1884_GER | B50: Togoland | C50: 18840705 | D50: 19161227 | E50: #5EB0DF | F50: Dependent | G50: Germany | H50: Africa | I50: NA | J50: =IF( F50 = "Sovereign", "x", "" ) | K50: =( $C50<=$Q$1 )*( $D50 > $Q$1 ) * 1 -> 0 | M50: Togoland Protectorate | N50: Bagida | O50: 49
A51: TOG_1916_FRA | B51: French Togoland | C51: 19161227 | D51: 19560910 | E51: #BFE6FF | F51: Dependent | G51: France | H51: Africa | I51: TOG_1884_GER | J51: =IF( F51 = "Sovereign", "x", "" ) | K51: =( $C51<=$Q$1 )*( $D51 > $Q$1 ) * 1 -> 0 | M51: Territory of Togoland | N51: Lome | O51: 50
A52: SRL_1961 | B52: Sierra Leone | C52: 19610427 | D52: 20261231 | E52: #a65628 | F52: Sovereign | H52: Africa | I52: SRL_1808_UK | J52: =IF( F52 = "Sovereign", "x", "" ) -> x | K52: =( $C52<=$Q$1 )*( $D52 > $Q$1 ) * 1 -> 1 | M52: Republic of Seirra Leone | N52: Freetown | O52: 51
A53: SRL_1808_UK | B53: British Sierra Leone | C53: 18080101 | D53: 19610427 | E53: #FFEEBA | F53: Dependent | G53: United Kingdom | H53: Africa | I53: NA | J53: =IF( F53 = "Sovereign", "x", "" ) | K53: =( $C53<=$Q$1 )*( $D53 > $Q$1 ) * 1 -> 0 | M53: Colony of Sierra Leone | N53: Freetown | O53: 52
A54: MAL_1960 | B54: Mali | C54: 19600820 | D54: 20261231 | E54: #f781bf | F54: Sovereign | H54: Africa | I54: MLF_1960 | J54: =IF( F54 = "Sovereign", "x", "" ) -> x | K54: =( $C54<=$Q$1 )*( $D54 > $Q$1 ) * 1 -> 1 | M54: Republic of Mali | N54: Bamako | O54: 53
A55: MAL_1958_FRA | B55: Sudanese Republic | C55: 19581124 | D55: 19600620 | E55: #BFE6FF | F55: Dependent | G55: France | H55: Africa | I55: MAL_1880_FRA | J55: =IF( F55 = "Sovereign", "x", "" ) | K55: =( $C55<=$Q$1 )*( $D55 > $Q$1 ) * 1 -> 0 | M55: Sudanese Republic | N55: Bamako | O55: 54
A56: MAL_1890_FRA | B56: French Sudan | C56: 18900818 | D56: 18951027 | E56: #BFE6FF | F56: Dependent | G56: France | H56: Africa | I56: NA | J56: =IF( F56 = "Sovereign", "x", "" ) | K56: =( $C56<=$Q$1 )*( $D56 > $Q$1 ) * 1 -> 0 | M56: French Sudan | N56: Bamako | O56: 55
A57: BUR_1960 | B57: Burkina Faso | C57: 19600805 | D57: 20261231 | E57: #999999 | F57: Sovereign | H57: Africa | I57: BUR_1958_FRA | J57: =IF( F57 = "Sovereign", "x", "" ) -> x | K57: =( $C57<=$Q$1 )*( $D57 > $Q$1 ) * 1 -> 1 | M57: Burkina Faso | N57: Ouagadougou | O57: 56
A58: BUR_1958_FRA | B58: French Upper Volta | C58: 19581211 | D58: 19600805 | E58: #BFE6FF | F58: Dependent | G58: France | H58: Africa | I58: FWA_1895_FRA | J58: =IF( F58 = "Sovereign", "x", "" ) | K58: =( $C58<=$Q$1 )*( $D58 > $Q$1 ) * 1 -> 0 | M58: Republic of Upper Volta | N58: Ouagadougou | O58: 57
A59: NGR_1960 | B59: Niger | C59: 19600803 | D59: 20261231 | E59: #66c2a5 | F59: Sovereign | H59: Africa | I59: NGR_1958_FRA | J59: =IF( F59 = "Sovereign", "x", "" ) -> x | K59: =( $C59<=$Q$1 )*( $D59 > $Q$1 ) * 1 -> 1 | M59: Republic of Niger | N59: Niamey | O59: 58
A60: NGR_1958_FRA | B60: Niger | C60: 19581218 | D60: 19600803 | E60: #BFE6FF | F60: Dependent | G60: France | H60: Africa | I60: FWA_1895_FRA | J60: =IF( F60 = "Sovereign", "x", "" ) | K60: =( $C60<=$Q$1 )*( $D60 > $Q$1 ) * 1 -> 0 | M60: Republic of Niger | N60: Niamey | O60: 59
A61: BEN_1960 | B61: Benin | C61: 19600801 | D61: 20261231 | E61: #fc8d62 | F61: Sovereign | H61: Africa | I61: BEN_1958_FRA | J61: =IF( F61 = "Sovereign", "x", "" ) -> x | K61: =( $C61<=$Q$1 )*( $D61 > $Q$1 ) * 1 -> 1 | M61: Republic of Benin | N61: Porto Novo | O61: 60
A62: BEN_1958_FRA | B62: Benin | C62: 19581204 | D62: 19600801 | E62: #BFE6FF | F62: Dependent | G62: France | H62: Africa | I62: FWA_1895_FRA | J62: =IF( F62 = "Sovereign", "x", "" ) | K62: =( $C62<=$Q$1 )*( $D62 > $Q$1 ) * 1 -> 0 | M62: Colony of Dahomey and Dependencies | N62: Porto Novo | O62: 61
A63: GHA_1821_UK | B63: Gold Coast | C63: 18210101 | D63: 19570306 | E63: #FFEEBA | F63: Dependent | G63: United Kingdom | H63: Africa | I63: NA | J63: =IF( F63 = "Sovereign", "x", "" ) | K63: =( $C63<=$Q$1 )*( $D63 > $Q$1 ) * 1 -> 0 | M63: Gold Coast | N63: Cape Coast | O63: 62
A64: NGA_1960 | B64: Nigeria | C64: 19601001 | D64: 20261231 | E64: #8da0cb | F64: Sovereign | H64: Africa | I64: NGA_1914_UK | J64: =IF( F64 = "Sovereign", "x", "" ) -> x | K64: =( $C64<=$Q$1 )*( $D64 > $Q$1 ) * 1 -> 1 | M64: Republic of Nigeria | N64: Abuja | O64: 63
A65: NGA_1914_UK | B65: Nigeria | C65: 19140101 | D65: 19601001 | E65: #FFEEBA | F65: Dependent | G65: United Kingdom | H65: Africa | I65: NNG_1900_UK/SNG_1900_UK | J65: =IF( F65 = "Sovereign", "x", "" ) | K65: =( $C65<=$Q$1 )*( $D65 > $Q$1 ) * 1 -> 0 | M65: Colony and Protectorate of Nigeria | N65: Lagos | O65: 64
A66: NNG_1900_UK | B66: Northern Nigeria | C66: 19000101 | D66: 19140101 | E66: #FFEEBA | F66: Dependent | G66: United Kingdom | H66: Africa | I66: NA | J66: =IF( F66 = "Sovereign", "x", "" ) | K66: =( $C66<=$Q$1 )*( $D66 > $Q$1 ) * 1 -> 0 | M66: Northern Nigeria Protectorate | N66: Zungeru | O66: 65
A67: SNG_1900_UK | B67: Southern Nigeria | C67: 19000101 | D67: 19140101 | E67: #FFEEBA | F67: Dependent | G67: United Kingdom | H67: Africa | I67: NA | J67: =IF( F67 = "Sovereign", "x", "" ) | K67: =( $C67<=$Q$1 )*( $D67 > $Q$1 ) * 1 -> 0 | M67: Southern Nigeria Protectorate | N67: Lagos | O67: 66
A68: CHD_1958_FRA | B68: French Chad | C68: 19581128 | D68: 19600811 | E68: #BFE6FF | F68: Dependent | G68: France | H68: Africa | I68: FEA_1910_FRA | J68: =IF( F68 = "Sovereign", "x", "" ) | K68: =( $C68<=$Q$1 )*( $D68 > $Q$1 ) * 1 -> 0 | L68: x | O68: 67
A69: EQG_1968 | B69: Equatorial Guinea | C69: 19681012 | D69: 20261231 | E69: #e78ac3 | F69: Sovereign | H69: Africa | I69: EQG_1959_SPA | J69: =IF( F69 = "Sovereign", "x", "" ) -> x | K69: =( $C69<=$Q$1 )*( $D69 > $Q$1 ) * 1 -> 1 | M69: Republic of Equatorial Guinea | N69: Ciudad de la Paz | O69: 68
A70: EQG_1959_SPA | B70: Spanish Guinea | C70: 19590730 | D70: 19681012 | E70: #FF9A8F | F70: Dependent | G70: Spain | H70: Africa | I70: EQG_1900_SPA | J70: =IF( F70 = "Sovereign", "x", "" ) | K70: =( $C70<=$Q$1 )*( $D70 > $Q$1 ) * 1 -> 0 | M70: Republic of Equatorial Guinea | N70: Ciudad de la Paz | O70: 69
A71: EQG_1900_SPA | B71: Spanish Guinea | C71: 19000627 | D71: 19590730 | E71: #FF9A8F | F71: Dependent | G71: Spain | H71: Africa | I71: NA | J71: =IF( F71 = "Sovereign", "x", "" ) | K71: =( $C71<=$Q$1 )*( $D71 > $Q$1 ) * 1 -> 0 | M71: Spanish Guinea | N71: Santa Isabel | O71: 70
A72: STP_1975 | B72: Sao Tome and Principe | C72: 19750712 | D72: 20261231 | E72: #a6d854 | F72: Sovereign | H72: Africa | I72: STP_1485_POR | J72: =IF( F72 = "Sovereign", "x", "" ) -> x | K72: =( $C72<=$Q$1 )*( $D72 > $Q$1 ) * 1 -> 1 | M72: Democratic Republic of Sao Tome and Principe | N72: Sao Tome | O72: 71
A73: STP_1485_POR | B73: Sao Tome and Principe | C73: 14850101 | D73: 19750712 | E73: #C98DE2 | F73: Dependent | G73: Portugal | H73: Africa | I73: NA | J73: =IF( F73 = "Sovereign", "x", "" ) | K73: =( $C73<=$Q$1 )*( $D73 > $Q$1 ) * 1 -> 0 | M73: Portuguese Sao Tome and Principe | N73: Sao Tome | O73: 72
A74: SEY_1976 | B74: Seychelles | C74: 19760629 | D74: 20261231 | E74: #ffd92f | F74: Sovereign | H74: Africa | I74: SEY_1814_UK | J74: =IF( F74 = "Sovereign", "x", "" ) -> x | K74: =( $C74<=$Q$1 )*( $D74 > $Q$1 ) * 1 -> 1 | M74: Republic of Seychelles | N74: Victoria | O74: 73
A75: SEY_1814_UK | B75: Seychelles | C75: 18140430 | D75: 19760629 | E75: #FFEEBA | F75: Dependent | G75: United Kingdom | H75: Africa | I75: SEY_1756_FRA | J75: =IF( F75 = "Sovereign", "x", "" ) | K75: =( $C75<=$Q$1 )*( $D75 > $Q$1 ) * 1 -> 0 | M75: Colony of Seychelles | N75: Victoria | O75: 74
A76: SEY_1756_FRA | B76: Seychelles | C76: 17561101 | D76: 18140430 | E76: #BFE6FF | F76: Dependent | G76: France | H76: Africa | I76: NA | J76: =IF( F76 = "Sovereign", "x", "" ) | K76: =( $C76<=$Q$1 )*( $D76 > $Q$1 ) * 1 -> 0 | M76: Colony of Seychelles | N76: Victoria | O76: 75
A77: ANG_1975 | B77: Angola | C77: 19751111 | D77: 20261231 | E77: #e5c494 | F77: Sovereign | H77: Africa | I77: ANG_1891_POR | J77: =IF( F77 = "Sovereign", "x", "" ) -> x | K77: =( $C77<=$Q$1 )*( $D77 > $Q$1 ) * 1 -> 1 | M77: Republic of Angola | N77: Luanda | O77: 76
A78: ANG_1891_POR | B78: Portuguese Angola | C78: 18910611 | D78: 19751111 | E78: #C98DE2 | F78: Dependent | G78: Portugal | H78: Africa | I78: NA | J78: =IF( F78 = "Sovereign", "x", "" ) | K78: =( $C78<=$Q$1 )*( $D78 > $Q$1 ) * 1 -> 0 | M78: Province of Angola | N78: Luanda | O78: 77
A79: DRC_1960 | B79: Republic of the Congo | C79: 19600630 | D79: 20261231 | E79: #e41a1c | F79: Sovereign | H79: Africa | I79: CON_1923_BEL | J79: =IF( F79 = "Sovereign", "x", "" ) -> x | K79: =( $C79<=$Q$1 )*( $D79 > $Q$1 ) * 1 -> 1 | M79: Republic of the Congo | N79: Leopoldville | O79: 78
A80: CON_1908_BEL | B80: Belgian Congo | C80: 19081115 | D80: 19600630 | E80: #377eb8 | F80: Dependent | G80: Belgium | H80: Africa | I80: CFS_1886 | J80: =IF( F80 = "Sovereign", "x", "" ) | K80: =( $C80<=$Q$1 )*( $D80 > $Q$1 ) * 1 -> 0 | M80: Belgian Congo | N80: Boma | O80: 79
A81: CON_1885 | B81: Congo Free State | C81: 18850701 | D81: 19081115 | E81: #4daf4a | F81: Sovereign | H81: Africa | I81: NA | J81: =IF( F81 = "Sovereign", "x", "" ) -> x | K81: =( $C81<=$Q$1 )*( $D81 > $Q$1 ) * 1 -> 0 | M81: Congo Free State | N81: Vivi | O81: 80
A82: CAM_1961 | B82: Cameroon | C82: 19611001 | D82: 20261231 | E82: #984ea3 | F82: Sovereign | H82: Africa | I82: CAM_1916_FRA/CAM_1916_UK | J82: =IF( F82 = "Sovereign", "x", "" ) -> x | K82: =( $C82<=$Q$1 )*( $D82 > $Q$1 ) * 1 -> 1 | M82: Republic of Cameroon | N82: Yaounde | O82: 81
A83: CAM_1916_UK | B83: British Cameroons | C83: 19160720 | D83: 19611001 | E83: #FFEEBA | F83: Dependent | G83: United Kingdom | H83: Africa | I83: CAM_1884_GER | J83: =IF( F83 = "Sovereign", "x", "" ) | K83: =( $C83<=$Q$1 )*( $D83 > $Q$1 ) * 1 -> 0 | M83: British Cameroon | N83: Buea | O83: 82
A84: CAM_1916_FRA | B84: French Cameroon | C84: 19160720 | D84: 19600101 | E84: #BFE6FF | F84: Dependent | G84: France | H84: Africa | I84: CAM_1884_GER | J84: =IF( F84 = "Sovereign", "x", "" ) | K84: =( $C84<=$Q$1 )*( $D84 > $Q$1 ) * 1 -> 0 | M84: French Cameroon | N84: Yaounde | O84: 83
A85: CAM_1884_GER | B85: Kamerun | C85: 18840817 | D85: 19160720 | E85: #5EB0DF | F85: Dependent | G85: Germany | H85: Africa | I85: NA | J85: =IF( F85 = "Sovereign", "x", "" ) | K85: =( $C85<=$Q$1 )*( $D85 > $Q$1 ) * 1 -> 0 | M85: Kamerun | N85: Jaunde | O85: 84
A86: NAM_1990 | B86: Namibia | C86: 19900321 | D86: 20261231 | E86: #ff7f00 | F86: Sovereign | H86: Africa | I86: SWA_1915_SA | J86: =IF( F86 = "Sovereign", "x", "" ) -> x | K86: =( $C86<=$Q$1 )*( $D86 > $Q$1 ) * 1 -> 1 | M86: Republic of Namibia | N86: Windhoek | O86: 85
A87: SWA_1915_SA | B87: South West Africa | C87: 19150709 | D87: 19900321 | E87: #ffff33 | F87: Dependent | G87: South Africa | H87: Africa | I87: SWA_1884_GER | J87: =IF( F87 = "Sovereign", "x", "" ) | K87: =( $C87<=$Q$1 )*( $D87 > $Q$1 ) * 1 -> 0 | M87: South West Africa | N87: Windhoek | O87: 86
A88: SWA_1884_GER | B88: German South West Africa | C88: 18840807 | D88: 19150709 | E88: #5EB0DF | F88: Dependent | G88: Germany | H88: Africa | I88: NA | J88: =IF( F88 = "Sovereign", "x", "" ) | K88: =( $C88<=$Q$1 )*( $D88 > $Q$1 ) * 1 -> 0 | M88: German South West Africa | N88: Windhuk | O88: 87
A89: BOT_1966 | B89: Botswana | C89: 19660930 | D89: 20261231 | E89: #a65628 | F89: Sovereign | H89: Africa | I89: BOT_1885_UK | J89: =IF( F89 = "Sovereign", "x", "" ) -> x | K89: =( $C89<=$Q$1 )*( $D89 > $Q$1 ) * 1 -> 1 | N89: Gabarone | O89: 88
A90: BOT_1885_UK | B90: Bechuanaland Protectorate | C90: 18850331 | D90: 19660930 | E90: #FFEEBA | F90: Dependent | G90: United Kingdom | H90: Africa | I90: NA | J90: =IF( F90 = "Sovereign", "x", "" ) | K90: =( $C90<=$Q$1 )*( $D90 > $Q$1 ) * 1 -> 0 | N90: Gabarone | O90: 89
A91: SAF_1910 | B91: South Africa | C91: 19100531 | D91: 20261231 | E91: #f781bf | F91: Sovereign | H91: Africa | I91: NAT_1843/TRV_1902_UK/OFS_1902_UK/CAP_1806_UK | J91: =IF( F91 = "Sovereign", "x", "" ) -> x | K91: =( $C91<=$Q$1 )*( $D91 > $Q$1 ) * 1 -> 1 | N91: Pretoria | O91: 90
A92: ESW_1968 | B92: Eswatini | C92: 19680924 | D92: 20261231 | E92: #999999 | F92: Sovereign | H92: Africa | I92: ESW_1903_UK | J92: =IF( F92 = "Sovereign", "x", "" ) -> x | K92: =( $C92<=$Q$1 )*( $D92 > $Q$1 ) * 1 -> 1 | N92: Mbabane | O92: 91
A93: ESW_1903_UK | B93: Swaziland | C93: 19030101 | D93: 19680924 | E93: #FFEEBA | F93: Dependent | G93: United Kingdom | H93: Africa | I93: NA | J93: =IF( F93 = "Sovereign", "x", "" ) | K93: =( $C93<=$Q$1 )*( $D93 > $Q$1 ) * 1 -> 0 | O93: 92
A94: NAT_1843_UK | B94: Natal | C94: 18430504 | D94: 19100531 | E94: #FFEEBA | F94: Dependent | G94: United Kingdom | H94: Africa | I94: NA | J94: =IF( F94 = "Sovereign", "x", "" ) | K94: =( $C94<=$Q$1 )*( $D94 > $Q$1 ) * 1 -> 0 | O94: 93
A95: LES_1966 | B95: Lesotho | C95: 19661004 | D95: 20261231 | E95: #66c2a5 | F95: Sovereign | H95: Africa | I95: LES_1885_UK | J95: =IF( F95 = "Sovereign", "x", "" ) -> x | K95: =( $C95<=$Q$1 )*( $D95 > $Q$1 ) * 1 -> 1 | M95: Kingdom of Lesotho | N95: Maseru | O95: 94
A96: LES_1884_UK | B96: Basutoland | C96: 18840318 | D96: 19661004 | E96: #FFEEBA | F96: Dependent | G96: United Kingdom | H96: Africa | I96: CAP_1806_UK | J96: =IF( F96 = "Sovereign", "x", "" ) | K96: =( $C96<=$Q$1 )*( $D96 > $Q$1 ) * 1 -> 0 | M96: Colony of Basutoland | N96: Maseru | O96: 95
A97: CAP_1806_UK | B97: Cape Colony | C97: 18060108 | D97: 19100531 | E97: #FFEEBA | F97: Dependent | G97: United Kingdom | H97: Africa | I97: NA | J97: =IF( F97 = "Sovereign", "x", "" ) | K97: =( $C97<=$Q$1 )*( $D97 > $Q$1 ) * 1 -> 0 | M97: Cape Colony | N97: Cape Town | O97: 96
A98: TRV_1902_UK | B98: Transvaal | C98: 19020531 | D98: 19100531 | E98: #FFEEBA | F98: Dependent | G98: United Kingdom | H98: Africa | I98: NA | J98: =IF( F98 = "Sovereign", "x", "" ) | K98: =( $C98<=$Q$1 )*( $D98 > $Q$1 ) * 1 -> 0 | O98: 97
A99: OFS_1902_UK | B99: Orange River | C99: 19020531 | D99: 19100531 | E99: #FFEEBA | F99: Dependent | G99: United Kingdom | H99: Africa | I99: NA | J99: =IF( F99 = "Sovereign", "x", "" ) | K99: =( $C99<=$Q$1 )*( $D99 > $Q$1 ) * 1 -> 0 | O99: 98
A100: ZAM_1964 | B100: Zambia | C100: 19641024 | D100: 20261231 | E100: #fc8d62 | F100: Sovereign | H100: Africa | I100: ZAM_1963_UK | J100: =IF( F100 = "Sovereign", "x", "" ) -> x | K100: =( $C100<=$Q$1 )*( $D100 > $Q$1 ) * 1 -> 1 | M100: Republic of Zambia | N100: Lusaka | O100: 99
...

Sheet Capitals
A1: ID | B1: Begin | C1: End | D1: Capital | E1: Lat | F1: Lon | G1: Wiki Coords | H1: Checked
A2: DJI_1977 | B2: 19770627 | C2: 20261231 | D2: Djibouti | E2: =11+36/60 -> 11.6 | F2: =43+10/60 -> 43.166667 | G2: 11°36′N 43°10′E | H2: =VLOOKUP( $A2, Sovereignty!$A$2:$L$510, 12, 0 ) -> x
A3: DJI_1862_FRA | B3: 19670705 | C3: 19770627 | D3: Djibouti | E3: =11+36/60 -> 11.6 | F3: =43+10/60 -> 43.166667 | G3: 11°36′N 43°10′E | H3: =VLOOKUP( $A3, Sovereignty!$A$2:$L$510, 12, 0 ) -> x
A4: DJI_1862_FRA | B4: 18960520 | C4: 19670705 | D4: Djibouti | E4: =11+36/60 -> 11.6 | F4: =43+10/60 -> 43.166667 | G4: 11°36′N 43°10′E | H4: =VLOOKUP( $A4, Sovereignty!$A$2:$L$510, 12, 0 ) -> x
A5: DJI_1862_FRA | B5: 18620311 | C5: 18960520 | D5: Obock | E5: =11+58/60 -> 11.966667 | F5: =43+17/60 -> 43.283333 | G5: 11°58′N 43°17′E | H5: =VLOOKUP( $A5, Sovereignty!$A$2:$L$510, 12, 0 ) -> x
A6: SOM_1960 | B6: 19600626 | C6: 20261231 | D6: Mogadishu | E6: =2+2/60+21/3600 -> 2.0391667 | F6: =45+20/60+31/3600 -> 45.341944 | G6: 02°02′21″N 45°20′31″E | H6: =VLOOKUP( $A6, Sovereignty!$A$2:$L$510, 12, 0 ) -> x
A7: SOL_1884_UK | B7: 18840101 | C7: 19410315 | D7: Berbera | E7: =10+26/60+8/3600 -> 10.435556 | F7: =45+59/3600 -> 45.016389 | G7: 10°26′08″N 045°00′59″E | H7: =VLOOKUP( $A7, Sovereignty!$A$2:$L$510, 12, 0 ) -> x
A8: SOL_1884_UK | B8: 19410315 | C8: 19600626 | D8: Hergeisa | E8: =9+33/60+40/3600 -> 9.5611111 | F8: =44+4/60 -> 44.066667 | G8: 9°33′40″N 44°04′00″E | H8: =VLOOKUP( $A8, Sovereignty!$A$2:$L$510, 12, 0 ) -> x
A9: SOM_1950_ITA | B9: 19500401 | C9: 19600701 | D9: Mogadishu | E9: =2+2/60+21/3600 -> 2.0391667 | F9: =45+20/60+31/3600 -> 45.341944 | G9: 02°02′21″N 45°20′31″E | H9: =VLOOKUP( $A9, Sovereignty!$A$2:$L$510, 12, 0 ) -> x
A10: SOM_1941_UK | B10: 19410225 | C10: 19500401 | D10: Mogadishu | E10: =2+2/60+21/3600 -> 2.0391667 | F10: =45+20/60+31/3600 -> 45.341944 | G10: 02°02′21″N 45°20′31″E | H10: =VLOOKUP( $A10, Sovereignty!$A$2:$L$510, 12, 0 ) -> x
A11: IEA_1936_ITA | B11: 19360509 | C11: 19411127 | D11: Addis Ababa | E11: =9+1/60+48/3600 -> 9.03 | F11: =38+44/60+24/3600 -> 38.74 | G11: 9°1′48″N 38°44′24″E | H11: =VLOOKUP( $A11, Sovereignty!$A$2:$L$510, 12, 0 ) -> x
A12: SOM_1889_ITA | B12: 18890208 | C12: 19360601 | D12: Mogadishu | E12: =2+2/60+21/3600 -> 2.0391667 | F12: =45+20/60+31/3600 -> 45.341944 | G12: 02°02′21″N 45°20′31″E | H12: =VLOOKUP( $A12, Sovereignty!$A$2:$L$510, 12, 0 ) -> x
A13: ERI_1993 | B13: 19930524 | C13: 20261231 | D13: Asmara | E13: =15+20/60+9/3600 -> 15.335833 | F13: =38+56/60+28/3600 -> 38.941111 | G13: 15°20′09″N 38°56′28″E | H13: =VLOOKUP( $A13, Sovereignty!$A$2:$L$510, 12, 0 ) -> x
A14: ERI_1952 | B14: 19520915 | C14: 19621114 | D14: Asmara | E14: =15+20/60+9/3600 -> 15.335833 | F14: =38+56/60+28/3600 -> 38.941111 | G14: 15°20′09″N 38°56′28″E | H14: =VLOOKUP( $A14, Sovereignty!$A$2:$L$510, 12, 0 ) -> x
A15: ERI_1941_UK | B15: 19411127 | C15: 19520915 | D15: Asmara | E15: =15+20/60+9/3600 -> 15.335833 | F15: =38+56/60+28/3600 -> 38.941111 | G15: 15°20′09″N 38°56′28″E | H15: =VLOOKUP( $A15, Sovereignty!$A$2:$L$510, 12, 0 ) -> x
A16: ERI_1882_ITA | B16: 18820705 | C16: 19360601 | D16: Asmara | E16: =15+20/60+9/3600 -> 15.335833 | F16: =38+56/60+28/3600 -> 38.941111 | G16: 15°20′09″N 38°56′28″E | H16: =VLOOKUP( $A16, Sovereignty!$A$2:$L$510, 12, 0 ) -> x
A17: ETH_1941 | B17: 19411127 | C17: 20261231 | D17: Addis Ababa | E17: =9+1/60+48/3600 -> 9.03 | F17: =38+44/60+24/3600 -> 38.74 | G17: 9°1′48″N 38°44′24″E | H17: =VLOOKUP( $A17, Sovereignty!$A$2:$L$510, 12, 0 ) -> x
A18: ETH_1855 | B18: 18890101 | C18: 19360509 | D18: Addis Ababa | E18: =9+1/60+48/3600 -> 9.03 | F18: =38+44/60+24/3600 -> 38.74 | G18: 9°1′48″N 38°44′24″E | H18: =VLOOKUP( $A18, Sovereignty!$A$2:$L$510, 12, 0 ) -> x
A19: ETH_1855 | B19: 18810101 | C19: 18890101 | D19: Mekelle | E19: =13+29/60+49/3600 -> 13.496944 | F19: =39+28/60+37/3600 -> 39.476944 | G19: 13°29′49″N 39°28′37″E | H19: =VLOOKUP( $A19, Sovereignty!$A$2:$L$510, 12, 0 ) -> x
A20: ETH_1855 | B20: 18550211 | C20: 18810101 | D20: Debre Tabor | E20: =11+51/60 -> 11.85 | F20: =38+1/60 -> 38.016667 | G20: 11°51′N 38°1′E | H20: =VLOOKUP( $A20, Sovereignty!$A$2:$L$510, 12, 0 ) -> x
A21: CON_1960 | B21: 19600815 | C21: 20261231 | D21: Brazzaville | E21: =-4-16/60 -> -4.2666667 | F21: =15+16/60 -> 15.266667 | G21: 4°16′S 15°16′E | H21: =VLOOKUP( $A21, Sovereignty!$A$2:$L$510, 12, 0 ) -> x
A22: CON_1958_FRA | B22: 19581128 | C22: 19600815 | D22: Brazzaville | E22: =-4-16/60 -> -4.2666667 | F22: =15+16/60 -> 15.266667 | G22: 4°16′S 15°16′E | H22: =VLOOKUP( $A22, Sovereignty!$A$2:$L$510, 12, 0 ) -> x
A23: FEA_1910_FRA | B23: 19100115 | C23: 19581128 | D23: Brazzaville | E23: =-4-16/60 -> -4.2666667 | F23: =15+16/60 -> 15.266667 | G23: 4°16′S 15°16′E | H23: =VLOOKUP( $A23, Sovereignty!$A$2:$L$510, 12, 0 ) -> x
A24: CON_1882_FRA | B24: 18821130 | C24: 19100115 | D24: Brazzaville | E24: =-4-16/60 -> -4.2666667 | F24: =15+16/60 -> 15.266667 | G24: 4°16′S 15°16′E | H24: =VLOOKUP( $A24, Sovereignty!$A$2:$L$510, 12, 0 ) -> x
A25: GAB_1960 | B25: 19600817 | C25: 20261231 | D25: Libreville | E25: =24/60+38/3600 -> 0.41055556 | F25: =9+26/60+25/3600 -> 9.4402778 | G25: 0°24′28″N 9°26′25″E | H25: =VLOOKUP( $A25, Sovereignty!$A$2:$L$510, 12, 0 ) -> x
A26: GAB_1958_FRA | B26: 19581128 | C26: 19600817 | D26: Libreville | E26: =24/60+38/3600 -> 0.41055556 | F26: =9+26/60+25/3600 -> 9.4402778 | G26: 0°24′28″N 9°26′25″E | H26: =VLOOKUP( $A26, Sovereignty!$A$2:$L$510, 12, 0 ) -> x
A27: GAB_1885_FRA | B27: 18880101 | C27: 19100115 | D27: Libreville | E27: =24/60+38/3600 -> 0.41055556 | F27: =9+26/60+25/3600 -> 9.4402778 | G27: 0°24′28″N 9°26′25″E | H27: =VLOOKUP( $A27, Sovereignty!$A$2:$L$510, 12, 0 ) -> x
A28: CAR_1960 | B28: 19600813 | C28: 20261231 | D28: Bangui | E28: =4+22/60+24/3600 -> 4.3733333 | F28: =18+33/60+46/3600 -> 18.562778 | G28: 04°22′24″N 18°33′46″E | H28: =VLOOKUP( $A28, Sovereignty!$A$2:$L$510, 12, 0 ) -> x
A29: CAR_1958_FRA | B29: 19581201 | C29: 19600813 | D29: Bangui | E29: =4+22/60+24/3600 -> 4.3733333 | F29: =18+33/60+46/3600 -> 18.562778 | G29: 04°22′24″N 18°33′46″E | H29: =VLOOKUP( $A29, Sovereignty!$A$2:$L$510, 12, 0 ) -> x
A30: CAR_1903_FRA | B30: 19061211 | C30: 19100115 | D30: Bangui | E30: =4+22/60+24/3600 -> 4.3733333 | F30: =18+33/60+46/3600 -> 18.562778 | G30: 04°22′24″N 18°33′46″E | H30: =VLOOKUP( $A30, Sovereignty!$A$2:$L$510, 12, 0 ) -> x
A31: CAR_1903_FRA | B31: 19060210 | C31: 19061211 | D31: Fort de Passel | E31: =5+1/60+29.7/3600 -> 5.0249167 | F31: =19+15/60+30.9/3600 -> 19.258583 | G31: 5°1′29.7″N 19°15′30.9″E | H31: =VLOOKUP( $A31, Sovereignty!$A$2:$L$510, 12, 0 ) -> x
A32: CAR_1903_FRA | B32: 19031229 | C32: 19060210 | D32: Abiras | E32: =4.135 -> 4.135 | F32: =22.44 -> 22.44 | G32: 4.135°N 22.440°E | H32: =VLOOKUP( $A32, Sovereignty!$A$2:$L$510, 12, 0 ) -> x
A33: CHD_1960 | B33: 19730406 | C33: 20261231 | D33: N'Djamena | E33: =12+6/60+19/3600 -> 12.105278 | F33: =15+2/60+41/3600 -> 15.044722 | G33: 12°06′19″N 15°02′41″E | H33: =VLOOKUP( $A33, Sovereignty!$A$2:$L$510, 12, 0 ) -> x
A34: CHD_1960 | B34: 19600811 | C34: 19730406 | D34: Fort Lamy | E34: =12+6/60+19/3600 -> 12.105278 | F34: =15+2/60+41/3600 -> 15.044722 | G34: 12°06′19″N 15°02′41″E | H34: =VLOOKUP( $A34, Sovereignty!$A$2:$L$510, 12, 0 ) -> x
A35: CHD_1900_FRA | B35: 19000905 | C35: 19100115 | D35: Fort Lamy | E35: =12+6/60+19/3600 -> 12.105278 | F35: =15+2/60+41/3600 -> 15.044722 | G35: 12°06′19″N 15°02′41″E | H35: =VLOOKUP( $A35, Sovereignty!$A$2:$L$510, 12, 0 ) -> x
A36: CHD_1958_FRA | B36: 19581128 | C36: 19600811 | D36: Fort Lamy | E36: =12+6/60+19/3600 -> 12.105278 | F36: =15+2/60+41/3600 -> 15.044722 | G36: 12°06′19″N 15°02′41″E | H36: =VLOOKUP( $A36, Sovereignty!$A$2:$L$510, 12, 0 ) -> x
A37: CPV_1975 | B37: 19750705 | C37: 20261231 | D37: Praia | E37: =14.918 -> 14.918 | F37: =-23.509 -> -23.509 | G37: 14.918°N 23.509°W | H37: =VLOOKUP( $A37, Sovereignty!$A$2:$L$510, 12, 0 ) -> x
A38: CPV_1462_POR | B38: 14620101 | C38: 19750705 | D38: Praia | E38: =14.918 -> 14.918 | F38: =-23.509 -> -23.509 | G38: 14.918°N 23.509°W | H38: =VLOOKUP( $A38, Sovereignty!$A$2:$L$510, 12, 0 ) -> x
A39: MRT_1960 | B39: 19601128 | C39: 20261231 | D39: Nouakchott | E39: =18+5/60+7/3600 -> 18.085278 | F39: =-15-58/60-21/3600 -> -15.9725 | G39: 18°05′07″N 15°58′21″W | H39: =VLOOKUP( $A39, Sovereignty!$A$2:$L$510, 12, 0 ) -> 0
A40: MRT_1958_FRA | B40: 19581128 | C40: 19601128 | D40: Nouakchott | E40: =18+5/60+7/3600 -> 18.085278 | F40: =-15-58/60-21/3600 -> -15.9725 | G40: 18°05′07″N 15°58′21″W | H40: =VLOOKUP( $A40, Sovereignty!$A$2:$L$510, 12, 0 ) -> 0
A41: FWA_1895_FRA | B41: 19020101 | C41: 19581218 | D41: Nouakchott | E41: =18+5/60+7/3600 -> 18.085278 | F41: =-15-58/60-21/3600 -> -15.9725 | G41: 18°05′07″N 15°58′21″W | H41: =VLOOKUP( $A41, Sovereignty!$A$2:$L$510, 12, 0 ) -> 0
A42: FWA_1895_FRA | B42: 18951027 | C42: 19020101 | D42: Saint Louis | E42: =16+2/60 -> 16.033333 | F42: =-16-30/60 -> -16.5 | G42: 16°02′N 16°30′W | H42: =VLOOKUP( $A42, Sovereignty!$A$2:$L$510, 12, 0 ) -> 0
A43: MLF_1960 | B43: 19600620 | C43: 19600820 | D43: Dakar | E43: =14+41/60+34/3600 -> 14.692778 | F43: =-17-26/60-48/3600 -> -17.446667 | G43: 14°41′34″N 17°26′48″W | H43: =VLOOKUP( $A43, Sovereignty!$A$2:$L$510, 12, 0 ) -> 0
A44: SEN_1960 | B44: 19600820 | C44: 20261231 | D44: Dakar | E44: =14+41/60+34/3600 -> 14.692778 | F44: =-17-26/60-48/3600 -> -17.446667 | G44: 14°41′34″N 17°26′48″W | H44: =VLOOKUP( $A44, Sovereignty!$A$2:$L$510, 12, 0 ) -> 0
A45: SEN_1958_FRA | B45: 19581125 | C45: 19600620 | D45: Dakar | E45: =14+41/60+34/3600 -> 14.692778 | F45: =-17-26/60-48/3600 -> -17.446667 | G45: 14°41′34″N 17°26′48″W | H45: =VLOOKUP( $A45, Sovereignty!$A$2:$L$510, 12, 0 ) -> 0
A46: GAM_1965 | B46: 19730424 | C46: 20261231 | D46: Banjul | E46: =13+27/60 -> 13.45 | F46: =-16-34/60-30/3600 -> -16.575 | G46: 13°27′00″N 16°34′30″W | H46: =VLOOKUP( $A46, Sovereignty!$A$2:$L$510, 12, 0 ) -> 0
A47: GAM_1965 | B47: 19650218 | C47: 19730424 | D47: Bathurst | E47: =13+27/60 -> 13.45 | F47: =-16-34/60-30/3600 -> -16.575 | G47: 13°27′00″N 16°34′30″W | H47: =VLOOKUP( $A47, Sovereignty!$A$2:$L$510, 12, 0 ) -> 0
A48: GAM_1816_UK | B48: 18161017 | C48: 19650218 | D48: Bathurst | E48: =13+27/60 -> 13.45 | F48: =-16-34/60-30/3600 -> -16.575 | G48: 13°27′00″N 16°34′30″W | H48: =VLOOKUP( $A48, Sovereignty!$A$2:$L$510, 12, 0 ) -> 0
A49: GUI_1958 | B49: 19581002 | C49: 20261231 | D49: Conakry | E49: =9+30/60+33/3600 -> 9.5091667 | F49: =-13-42/60-44/3600 -> -13.712222 | G49: 09°30′33″N 13°42′44″W | H49: =VLOOKUP( $A49, Sovereignty!$A$2:$L$510, 12, 0 ) -> 0
A50: GUI_1891_FRA | B50: 18910101 | C50: 18951027 | D50: Conakry | E50: =9+30/60+33/3600 -> 9.5091667 | F50: =-13-42/60-44/3600 -> -13.712222 | G50: 09°30′33″N 13°42′44″W | H50: =VLOOKUP( $A50, Sovereignty!$A$2:$L$510, 12, 0 ) -> 0
A51: GBS_1974 | B51: 19740910 | C51: 20261231 | D51: Bissau | E51: =11+51/60+36/3600 -> 11.86 | F51: =-15-35/60 -> -15.583333 | G51: 11°51′36″N 15°35′0″W | H51: =VLOOKUP( $A51, Sovereignty!$A$2:$L$510, 12, 0 ) -> 0
A52: GBS_1879_POR | B52: 18790101 | C52: 19740910 | D52: Bissau | E52: =11+51/60+36/3600 -> 11.86 | F52: =-15-35/60 -> -15.583333 | G52: 11°51′36″N 15°35′0″W | H52: =VLOOKUP( $A52, Sovereignty!$A$2:$L$510, 12, 0 ) -> 0
A53: LIB_1847 | B53: 18470726 | C53: 20261231 | D53: Monrovia | E53: =6+18/60+48/3600 -> 6.3133333 | F53: =-10-48/60-5/3600 -> -10.801389 | G53: 6°18′48″N 10°48′5″W | H53: =VLOOKUP( $A53, Sovereignty!$A$2:$L$510, 12, 0 ) -> 0
A54: LIB_1822_ACS | B54: 18220107 | C54: 18470726 | D54: Monrovia | E54: =6+18/60+48/3600 -> 6.3133333 | F54: =-10-48/60-5/3600 -> -10.801389 | G54: 6°18′48″N 10°48′5″W | H54: =VLOOKUP( $A54, Sovereignty!$A$2:$L$510, 12, 0 ) -> 0
A55: IVC_1960 | B55: 19830321 | C55: 20261231 | D55: Yamoussoukro | E55: =6+48/60+58/3600 -> 6.8161111 | F55: =-5+16/60+27/3600 -> -4.7258333 | G55: 06°48′58″N 05°16′27″W | H55: =VLOOKUP( $A55, Sovereignty!$A$2:$L$510, 12, 0 ) -> 0
A56: IVC_1960 | B56: 19600807 | C56: 19830321 | D56: Abidjan | E56: =5+19/60 -> 5.3166667 | F56: =-4-2/60 -> -4.0333333 | G56: 5°19′N 4°2′W | H56: =VLOOKUP( $A56, Sovereignty!$A$2:$L$510, 12, 0 ) -> 0
A57: IVC_1958_FRA | B57: 19581204 | C57: 19600807 | D57: Abidjan | E57: =5+19/60 -> 5.3166667 | F57: =-4-2/60 -> -4.0333333 | G57: 5°19′N 4°2′W | H57: =VLOOKUP( $A57, Sovereignty!$A$2:$L$510, 12, 0 ) -> 0
A58: IVC_1893_FRA | B58: 19340101 | C58: 19581204 | D58: Bingerville | E58: =5+21/60 -> 5.35 | F58: =-3-54/60 -> -3.9 | G58: 5°21′N 3°54′W | H58: =VLOOKUP( $A58, Sovereignty!$A$2:$L$510, 12, 0 ) -> 0
A59: IVC_1893_FRA | B59: 19000101 | C59: 19340101 | D59: Bingerville | E59: =5+21/60 -> 5.35 | F59: =-3-54/60 -> -3.9 | G59: 5°21′N 3°54′W | H59: =VLOOKUP( $A59, Sovereignty!$A$2:$L$510, 12, 0 ) -> 0
A60: IVC_1893_FRA | B60: 18930310 | C60: 19000101 | D60: Grand-Bassam | E60: =5+12/60 -> 5.2 | F60: =-3-44/60 -> -3.7333333 | G60: 5°12′N 3°44′W | H60: =VLOOKUP( $A60, Sovereignty!$A$2:$L$510, 12, 0 ) -> 0
A61: GHA_1957 | B61: 19570306 | C61: 20261231 | D61: Accra | E61: =5+33/60 -> 5.55 | F61: =-12/60 -> -0.2 | G61: 5°33′N 0°12′W | H61: =VLOOKUP( $A61, Sovereignty!$A$2:$L$510, 12, 0 ) -> 0
A62: TOG_1960 | B62: 19600427 | C62: 20261231 | D62: Lome | E62: =6+7/60+51/3600 -> 6.1308333 | F62: =1+12/60+55/3600 -> 1.2152778 | G62: 06°07′51″N 01°12′55″E | H62: =VLOOKUP( $A62, Sovereignty!$A$2:$L$510, 12, 0 ) -> 0
A63: TOG_1956_FRA | B63: 19560910 | C63: 19600427 | D63: Lome | E63: =6+7/60+51/3600 -> 6.1308333 | F63: =1+12/60+55/3600 -> 1.2152778 | G63: 06°07′51″N 01°12′55″E | H63: =VLOOKUP( $A63, Sovereignty!$A$2:$L$510, 12, 0 ) -> 0
A64: TOG_1884_GER | B64: 18970101 | C64: 19161227 | D64: Lome | E64: =6+7/60+51/3600 -> 6.1308333 | F64: =1+12/60+55/3600 -> 1.2152778 | G64: 06°07′51″N 01°12′55″E | H64: =VLOOKUP( $A64, Sovereignty!$A$2:$L$510, 12, 0 ) -> 0
A65: TOG_1884_GER | B65: 18870101 | C65: 18970101 | D65: Sebeab | E65: =6+25/60 -> 6.4166667 | F65: =1+37/60 -> 1.6166667 | G65: 6°15′N 1°37′E | H65: =VLOOKUP( $A65, Sovereignty!$A$2:$L$510, 12, 0 ) -> 0
A66: TOG_1884_GER | B66: 18840705 | C66: 18870101 | D66: Bagida | E66: =6+10/60 -> 6.1666667 | F66: =1+19/60 -> 1.3166667 | G66: 6°10′N 1°19′E | H66: =VLOOKUP( $A66, Sovereignty!$A$2:$L$510, 12, 0 ) -> 0
A67: TOG_1916_FRA | B67: 19161227 | C67: 19560910 | D67: Lome | E67: =6+7/60+51/3600 -> 6.1308333 | F67: =1+12/60+55/3600 -> 1.2152778 | G67: 06°07′51″N 01°12′55″E | H67: =VLOOKUP( $A67, Sovereignty!$A$2:$L$510, 12, 0 ) -> 0
A68: SRL_1961 | B68: 19610427 | C68: 20261231 | D68: Freetown | E68: =8+29/60+14/3600 -> 8.4872222 | F68: =-13-14/60-8/3600 -> -13.235556 | G68: 8°29′14″N 13°14′8″W | H68: =VLOOKUP( $A68, Sovereignty!$A$2:$L$510, 12, 0 ) -> 0
A69: SRL_1808_UK | B69: 18080101 | C69: 19610427 | D69: Freetown | E69: =8+29/60+14/3600 -> 8.4872222 | F69: =-13-14/60-8/3600 -> -13.235556 | G69: 8°29′14″N 13°14′8″W | H69: =VLOOKUP( $A69, Sovereignty!$A$2:$L$510, 12, 0 ) -> 0
A70: MAL_1960 | B70: 19600820 | C70: 20261231 | D70: Bamako | E70: =12+38/60+21/3600 -> 12.639167 | F70: =-8-10/3600 -> -8.0027778 | G70: 12°38′21″N 08°00′10″W | H70: =VLOOKUP( $A70, Sovereignty!$A$2:$L$510, 12, 0 ) -> 0
A71: MAL_1958_FRA | B71: 19581124 | C71: 19600620 | D71: Bamako | E71: =12+38/60+21/3600 -> 12.639167 | F71: =-8-10/3600 -> -8.0027778 | G71: 12°38′21″N 08°00′10″W | H71: =VLOOKUP( $A71, Sovereignty!$A$2:$L$510, 12, 0 ) -> 0
A72: MAL_1890_FRA | B72: 18900818 | C72: 19581124 | D72: Bamako | E72: =12+38/60+21/3600 -> 12.639167 | F72: =-8-10/3600 -> -8.0027778 | G72: 12°38′21″N 08°00′10″W | H72: =VLOOKUP( $A72, Sovereignty!$A$2:$L$510, 12, 0 ) -> 0
A73: BUR_1960 | B73: 19600805 | C73: 20261231 | D73: Ouagadougou | E73: =12+22/60+7/3600 -> 12.368611 | F73: =-1-31/60-39/3600 -> -1.5275 | G73: 12°22′07″N 01°31′39″W | H73: =VLOOKUP( $A73, Sovereignty!$A$2:$L$510, 12, 0 ) -> 0
A74: BUR_1958_FRA | B74: 19581211 | C74: 19600805 | D74: Ouagadougou | E74: =12+22/60+7/3600 -> 12.368611 | F74: =-1-31/60-39/3600 -> -1.5275 | G74: 12°22′07″N 01°31′39″W | H74: =VLOOKUP( $A74, Sovereignty!$A$2:$L$510, 12, 0 ) -> 0
A75: NGR_1960 | B75: 19600803 | C75: 20261231 | D75: Niamey | E75: =13+30/60+49/3600 -> 13.513611 | F75: =2+6/60+32/3600 -> 2.1088889 | G75: 13°30′49″N 02°06′32″E | H75: =VLOOKUP( $A75, Sovereignty!$A$2:$L$510, 12, 0 ) -> 0
A76: NGR_1958_FRA | B76: 19581218 | C76: 19600803 | D76: Niamey | E76: =13+30/60+49/3600 -> 13.513611 | F76: =2+6/60+32/3600 -> 2.1088889 | G76: 13°30′49″N 02°06′32″E | H76: =VLOOKUP( $A76, Sovereignty!$A$2:$L$510, 12, 0 ) -> 0
A77: BEN_1960 | B77: 19600801 | C77: 20261231 | D77: Porto Novo | E77: =6+29/60+50/3600 -> 6.4972222 | F77: =2+36/60+18/3600 -> 2.605 | G77: 6°29′50″N 2°36′18″E | H77: =VLOOKUP( $A77, Sovereignty!$A$2:$L$510, 12, 0 ) -> 0
A78: BEN_1958_FRA | B78: 19581204 | C78: 19600801 | D78: Porto Novo | E78: =6+29/60+50/3600 -> 6.4972222 | F78: =2+36/60+18/3600 -> 2.605 | G78: 6°29′50″N 2°36′18″E | H78: =VLOOKUP( $A78, Sovereignty!$A$2:$L$510, 12, 0 ) -> 0
A79: GHA_1821_UK | B79: 18770101 | C79: 19570306 | D79: Accra | E79: =5+33/60 -> 5.55 | F79: =-12/60 -> -0.2 | G79: 5°33′N 0°12′W | H79: =VLOOKUP( $A79, Sovereignty!$A$2:$L$510, 12, 0 ) -> 0
A80: GHA_1821_UK | B80: 18210101 | C80: 18770101 | D80: Cape Coast | E80: =5+6/60 -> 5.1 | F80: =-1-15/60 -> -1.25 | G80: 05°06′N 01°15′W | H80: =VLOOKUP( $A80, Sovereignty!$A$2:$L$510, 12, 0 ) -> 0
A81: NGA_1960 | B81: 19911212 | C81: 20261231 | D81: Abuja | E81: =9+4/60 -> 9.0666667 | F81: =7+29/60 -> 7.4833333 | G81: 9°4′N 7°29′E | H81: =VLOOKUP( $A81, Sovereignty!$A$2:$L$510, 12, 0 ) -> 0
A82: NGA_1960 | B82: 19541001 | C82: 19911212 | D82: Lagos | E82: =6+27/60+22/3600 -> 6.4561111 | F82: =3+23/60+37/3600 -> 3.3936111 | G82: 6°27′22″N 3°23′37″E | H82: =VLOOKUP( $A82, Sovereignty!$A$2:$L$510, 12, 0 ) -> 0
A83: NGA_1914_UK | B83: 19140101 | C83: 19541001 | D83: Lagos | E83: =6+27/60+22/3600 -> 6.4561111 | F83: =3+23/60+37/3600 -> 3.3936111 | G83: 6°27′22″N 3°23′37″E | H83: =VLOOKUP( $A83, Sovereignty!$A$2:$L$510, 12, 0 ) -> 0
A84: NNG_1900_UK | B84: 19000101 | C84: 19140101 | D84: Zungeru | E84: =9+48/60 -> 9.8 | F84: =6+9/60 -> 6.15 | G84: 9°48′N 6°9′E | H84: =VLOOKUP( $A84, Sovereignty!$A$2:$L$510, 12, 0 ) -> 0
A85: SNG_1900_UK | B85: 19000101 | C85: 19140101 | D85: Lagos | E85: =6+27/60+22/3600 -> 6.4561111 | F85: =3+23/60+37/3600 -> 3.3936111 | G85: 6°27′22″N 3°23′37″E | H85: =VLOOKUP( $A85, Sovereignty!$A$2:$L$510, 12, 0 ) -> 0
A86: EQG_1968 | B86: 20260102 | C86: 20261231 | D86: Ciudad de la Paz | E86: =1+35/60+20/3600 -> 1.5888889 | F86: =10+49/60+21/3600 -> 10.8225 | G86: 1°35′20″N 10°49′21″E | H86: =VLOOKUP( $A86, Sovereignty!$A$2:$L$510, 12, 0 ) -> 0
A87: EQG_1968 | B87: 19730712 | C87: 20260102 | D87: Malabo | E87: =3+44/60+44/3600 -> 3.7455556 | F87: =8+46/60+28/3600 -> 8.7744444 | G87: 3°44′44″N 8°46′28″E | H87: =VLOOKUP( $A87, Sovereignty!$A$2:$L$510, 12, 0 ) -> 0
A88: EQG_1968 | B88: 19681012 | C88: 19730712 | D88: Malabo | E88: =3+44/60+44/3600 -> 3.7455556 | F88: =8+46/60+28/3600 -> 8.7744444 | G88: 3°44′44″N 8°46′28″E | H88: =VLOOKUP( $A88, Sovereignty!$A$2:$L$510, 12, 0 ) -> 0
A89: EQG_1959_SPA | B89: 19590730 | C89: 19681012 | D89: Santa Isabel | E89: =3+44/60+44/3600 -> 3.7455556 | F89: =8+46/60+28/3600 -> 8.7744444 | G89: 3°44′44″N 8°46′28″E | H89: =VLOOKUP( $A89, Sovereignty!$A$2:$L$510, 12, 0 ) -> 0
A90: EQG_1900_SPA | B90: 19000627 | C90: 19590730 | D90: Santa Isabel | E90: =3+44/60+44/3600 -> 3.7455556 | F90: =8+46/60+28/3600 -> 8.7744444 | G90: 3°44′44″N 8°46′28″E | H90: =VLOOKUP( $A90, Sovereignty!$A$2:$L$510, 12, 0 ) -> 0
A91: STP_1975 | B91: 19750712 | C91: 20261231 | D91: Sao Tome | E91: =20/60 -> 0.33333333 | F91: =6+44/60 -> 6.7333333 | G91: 0°20′N 6°44′E | H91: =VLOOKUP( $A91, Sovereignty!$A$2:$L$510, 12, 0 ) -> 0
A92: STP_1485_POR | B92: 14850101 | C92: 19750712 | D92: Sao Tome | E92: =20/60 -> 0.33333333 | F92: =6+44/60 -> 6.7333333 | G92: 0°20′N 6°44′E | H92: =VLOOKUP( $A92, Sovereignty!$A$2:$L$510, 12, 0 ) -> 0
A93: SEY_1976 | B93: 19760629 | C93: 20261231 | D93: Victoria | E93: =-4-37/60-23/3600 -> -4.6230556 | F93: =55+27/60+9/3600 -> 55.4525 | G93: 4°37′23″S 55°27′09″E | H93: =VLOOKUP( $A93, Sovereignty!$A$2:$L$510, 12, 0 ) -> 0
A94: SEY_1814_UK | B94: 18410101 | C94: 19760629 | D94: Victoria | E94: =-4-37/60-23/3600 -> -4.6230556 | F94: =55+27/60+9/3600 -> 55.4525 | G94: 4°37′23″S 55°27′09″E | H94: =VLOOKUP( $A94, Sovereignty!$A$2:$L$510, 12, 0 ) -> 0
A95: SEY_1814_UK | B95: 18140430 | C95: 18410101 | D95: L'Etablissement | E95: =-4-37/60-23/3600 -> -4.6230556 | F95: =55+27/60+9/3600 -> 55.4525 | G95: 4°37′23″S 55°27′09″E | H95: =VLOOKUP( $A95, Sovereignty!$A$2:$L$510, 12, 0 ) -> 0
A96: SEY_1756_FRA | B96: 17780101 | C96: 18140430 | D96: L'Etablissement | E96: =-4-37/60-23/3600 -> -4.6230556 | F96: =55+27/60+9/3600 -> 55.4525 | G96: 4°37′23″S 55°27′09″E | H96: =VLOOKUP( $A96, Sovereignty!$A$2:$L$510, 12, 0 ) -> 0
A97: SEY_1756_FRA | B97: 17561101 | C97: 17780101 | H97: =VLOOKUP( $A97, Sovereignty!$A$2:$L$510, 12, 0 ) -> 0
A98: ANG_1975 | B98: 19751111 | C98: 20261231 | D98: Luanda | E98: =-8-50/60-18/3600 -> -8.8383333 | F98: =13+14/60+4/3600 -> 13.234444 | G98: 8°50′18″S 13°14′4″E | H98: =VLOOKUP( $A98, Sovereignty!$A$2:$L$510, 12, 0 ) -> 0
A99: ANG_1891_POR | B99: 18910611 | C99: 19751111 | D99: Luanda | E99: =-8-50/60-18/3600 -> -8.8383333 | F99: =13+14/60+4/3600 -> 13.234444 | G99: 8°50′18″S 13°14′4″E | H99: =VLOOKUP( $A99, Sovereignty!$A$2:$L$510, 12, 0 ) -> 0
A100: DRC_1960 | B100: 19660530 | C100: 20261231 | D100: Kinshasa | E100: =-4-19/60-19/3600 -> -4.3219444 | F100: =15+18/60+43/3600 -> 15.311944 | G100: 04°19′19″S 15°18′43″E | H100: =VLOOKUP( $A100, Sovereignty!$A$2:$L$510, 12, 0 ) -> 0
...

Sheet Names
A1: ID | B1: Begin | C1: End | D1: DisplayName | E1: OfficialName | F1: Checked
A2: DJI_1977 | B2: 19770627 | C2: 20261231 | D2: Djibouti | E2: Republic of Djibouti | F2: =VLOOKUP( $A2, Sovereignty!$A$2:$L$510, 12, 0 ) -> x
A3: DJI_1862_FRA | B3: 19670705 | C3: 19770627 | D3: Afars and Issas | E3: French Territory of the Afars and the Issas | F3: =VLOOKUP( $A3, Sovereignty!$A$2:$L$510, 12, 0 ) -> x
A4: DJI_1862_FRA | B4: 18960520 | C4: 19670705 | D4: French Somaliland | E4: French Somaliland | F4: =VLOOKUP( $A4, Sovereignty!$A$2:$L$510, 12, 0 ) -> x
A5: DJI_1862_FRA | B5: 18620311 | C5: 18960520 | D5: Obock Territory | E5: Obock Territory and Dependencies | F5: =VLOOKUP( $A5, Sovereignty!$A$2:$L$510, 12, 0 ) -> x
A6: SOM_1960 | B6: 19600626 | C6: 20261231 | D6: Somalia | E6: Federal Republic of Somalia | F6: =VLOOKUP( $A6, Sovereignty!$A$2:$L$510, 12, 0 ) -> x
A7: SOL_1884_UK | B7: 18840101 | C7: 19600626 | D7: British Somaliland | E7: Somaliland Protectorate | F7: =VLOOKUP( $A7, Sovereignty!$A$2:$L$510, 12, 0 ) -> x
A8: SOM_1950_ITA | B8: 19500401 | C8: 19600701 | D8: Somaliland | E8: Trust Territory of Somaliland | F8: =VLOOKUP( $A8, Sovereignty!$A$2:$L$510, 12, 0 ) -> x
A9: SOM_1941_UK | B9: 19411127 | C9: 19500401 | D9: Somaliland | E9: British Military Administration of Somaliland | F9: =VLOOKUP( $A9, Sovereignty!$A$2:$L$510, 12, 0 ) -> x
A10: IEA_1936_ITA | B10: 19360509 | C10: 19411127 | D10: Italian East Africa | E10: Italian East Africa | F10: =VLOOKUP( $A10, Sovereignty!$A$2:$L$510, 12, 0 ) -> x
A11: SOM_1889_ITA | B11: 18890208 | C11: 19360601 | D11: Italian Somaliland | E11: Italian Somaliland | F11: =VLOOKUP( $A11, Sovereignty!$A$2:$L$510, 12, 0 ) -> x
A12: ERI_1993 | B12: 19930524 | C12: 20261231 | D12: Eritrea | E12: State of Eritrea | F12: =VLOOKUP( $A12, Sovereignty!$A$2:$L$510, 12, 0 ) -> x
A13: ERI_1952 | B13: 19520915 | C13: 19621114 | D13: Eritrea | E13: Eritrea | F13: =VLOOKUP( $A13, Sovereignty!$A$2:$L$510, 12, 0 ) -> x
... A610: SEI_1571_SPA | B610: 15710101 | C610: 18981210 | D610: Spanish East Indies | E610: Spanish East Indies | F610: =VLOOKUP( $A610, Sovereignty!$A$2:$L$510, 12, 0 ) -> 0

Sheet Maps
A1: ID | B1: Begin | C1: End | D1: Map | E1: Checked | F1: Mapped | G1: Notes | J1: Made
A2: DJI_1977 | B2: 19770627 | C2: 20261231 | D2: Djibouti | E2: =VLOOKUP( $A2, Sovereignty!$A$2:$L$510, 12, 0 ) -> x
A3: DJI_1862_FRA | B3: 18960520 | C3: 19770627 | D3: Djibouti | E3: =VLOOKUP( $A3, Sovereignty!$A$2:$L$510, 12, 0 ) -> x
A4: DJI_1862_FRA | B4: 18620311 | C4: 18960520 | D4: Obock | E4: =VLOOKUP( $A4, Sovereignty!$A$2:$L$510, 12, 0 ) -> x | I4: Algeria | J4: x
A5: SOM_1960 | B5: 19600701 | C5: 20261231 | D5: BrSomaliaItSomalia | E5: =VLOOKUP( $A5, Sovereignty!$A$2:$L$510, 12, 0 ) -> x | I5: Angola | J5: x
A6: SOM_1960 | B6: 19600626 | C6: 19600701 | D6: BrSomalia | E6: =VLOOKUP( $A6, Sovereignty!$A$2:$L$510, 12, 0 ) -> x | I6: BC1BC2FC | J6: x
A7: SOL_1884_UK | B7: 18840101 | C7: 19600626 | D7: BrSomalia | E7: =VLOOKUP( $A7, Sovereignty!$A$2:$L$510, 12, 0 ) -> x | I7: Benin | J7: x
A8: SOM_1950_ITA | B8: 19500401 | C8: 19600701 | D8: ItSomalia | E8: =VLOOKUP( $A8, Sovereignty!$A$2:$L$510, 12, 0 ) -> x | I8: BenIvcMauNigBur | J8: x
A9: SOM_1941_UK | B9: 19411127 | C9: 19500401 | D9: ItSomalia | E9: =VLOOKUP( $A9, Sovereignty!$A$2:$L$510, 12, 0 ) -> x | I9: BenIvcNigBur | J9: x
A10: IEA_1936_ITA | B10: 19410225 | C10: 19411127 | D10: EthiopiaEritrea | E10: =VLOOKUP( $A10, Sovereignty!$A$2:$L$510, 12, 0 ) -> x | I10: Botswana | J10: x
A11: IEA_1936_ITA | B11: 19360601 | C11: 19410225 | D11: EthiopiaEritreaItSomalia | E11: =VLOOKUP( $A11, Sovereignty!$A$2:$L$510, 12, 0 ) -> x | I11: BritishCameroon | J11: x
A12: IEA_1936_ITA | B12: 19360509 | C12: 19360601 | D12: Ethiopia | E12: =VLOOKUP( $A12, Sovereignty!$A$2:$L$510, 12, 0 ) -> x | I12: BrSomalia | J12: x
A13: SOM_1889_ITA | B13: 18890208 | C13: 19360601 | D13: ItSomalia | E13: =VLOOKUP( $A13, Sovereignty!$A$2:$L$510, 12, 0 ) -> x | I13: BrSomaliaItSomalia | J13: x
A14: ERI_1993 | B14: 19930524 | C14: 20261231 | D14: Eritrea | E14: =VLOOKUP( $A14, Sovereignty!$A$2:$L$510, 12, 0 ) -> x | I14: BurkinaFaso | J14: x
A15: ERI_1952 | B15: 19520915 | C15: 19621114 | D15: Eritrea | E15: =VLOOKUP( $A15, Sovereignty!$A$2:$L$510, 12, 0 ) -> x | I15: Burundi | J15: x
... A100: CAM_1916_UK | B100: 19160720 | C100: 19611001 | D100: BritishCameroon | E100: =VLOOKUP( $A100, Sovereignty!$A$2:$L$510, 12, 0 ) -> 0 | I100: Zimbabwe | J100: x
A101: CAM_1916_FRA | B101: 19160720 | C101: 19601001 | D101: FrenchCameroon | E101: =VLOOKUP( $A101, Sovereignty!$A$2:$L$510, 12, 0 ) -> 0
A102: CAM_1884_GER | B102: 18840817 | C102: 19160720 | D102: BC1BC2FC | E102: =VLOOKUP( $A102, Sovereignty!$A$2:$L$510, 12, 0 ) -> 0
A103: NAM_1990 | B103: 19900321 | C103: 20261231 | D103: Namibia | E103: =VLOOKUP( $A103, Sovereignty!$A$2:$L$510, 12, 0 ) -> 0
A104: SWA_1915_SA | B104: 19150709 | C104: 19900321 | D104: Namibia | E104: =VLOOKUP( $A104, Sovereignty!$A$2:$L$510, 12, 0 ) -> 0
A105: SWA_1884_GER | B105: 18840807 | C105: 19150709 | D105: Namibia | E105: =VLOOKUP( $A105, Sovereignty!$A$2:$L$510, 12, 0 ) -> 0
A106: BOT_1966 | B106: 19660930 | C106: 20261231 | D106: Botswana | E106: =VLOOKUP( $A106, Sovereignty!$A$2:$L$510, 12, 0 ) -> 0
A107: BOT_1885_UK | B107: 18850331 | C107: 19660930 | D107: Botswana | E107: =VLOOKUP( $A107, Sovereignty!$A$2:$L$510, 12, 0 ) -> 0
A108: SAF_1910 | B108: 19100531 | C108: 20261231 | D108: SouthAfrica | E108: =VLOOKUP( $A108, Sovereignty!$A$2:$L$510, 12, 0 ) -> 0
A109: ESW_1968 | B109: 19680924 | C109: 20261231 | D109: Eswatini | E109: =VLOOKUP( $A109, Sovereignty!$A$2:$L$510, 12, 0 ) -> 0
A110: ESW_1903_UK | B110: 19030101 | C110: 19680924 | D110: Eswatini | E110: =VLOOKUP( $A110, Sovereignty!$A$2:$L$510, 12, 0 ) -> 0
A111: NAT_1843_UK | B111: 18430504 | C111: 19100531 | D111: Natal | E111: =VLOOKUP( $A111, Sovereignty!$A$2:$L$510, 12, 0 ) -> 0
A112: LES_1966 | B112: 19661004 | C112: 20261231 | D112: Lesotho | E112: =VLOOKUP( $A112, Sovereignty!$A$2:$L$510, 12, 0 ) -> 0
... A181: ALG_1516_OTT | B181: 15160101 | C181: 18300705 | D181: Algeria | E181: =VLOOKUP( $A181, Sovereignty!$A$2:$L$510, 12, 0 ) -> 0
A182: BRA_1822 | B182: 18220907 | C182: 20261231 | D182: ModernBrazil | E182: =VLOOKUP( $A182, Sovereignty!$A$2:$L$510, 12, 0 ) -> x | F182: x | G182: x | I182: Ar2Bo2 | J182: x
A183: BRA_1815 | B183: 18151216 | C183: 18220907 | D183: ModernBrazil | E183: =VLOOKUP( $A183, Sovereignty!$A$2:$L$510, 12, 0 ) -> x | F183: x | G183: x | I183: Ar2Bo2UruPar | J183: x
A184: BRA_1549_POR | B184: 15490101 | C184: 18151216 | D184: ModernBrazil | E184: =VLOOKUP( $A184, Sovereignty!$A$2:$L$510, 12, 0 ) -> x | F184: x | G184: x | I184: Ar2Bo2UruParPer | J184: x
A185: URU_1825 | B185: 18250825 | C185: 20261231 | D185: ModernUruguay | E185: =VLOOKUP( $A185, Sovereignty!$A$2:$L$510, 12, 0 ) -> x | F185: x | G185: x | I185: VicePeru | J185: x
A186: URU_1817_BRA | B186: 18170120 | C186: 18250825 | D186: ModernUruguay | E186: =VLOOKUP( $A186, Sovereignty!$A$2:$L$510, 12, 0 ) -> x | F186: x | G186: x | I186: Ar2Bo2Uru | J186: x
A187: UPR_1810 | B187: 18110514 | C187: 18160709 | D187: Ar2Bo2Uru | E187: =VLOOKUP( $A187, Sovereignty!$A$2:$L$510, 12, 0 ) -> x | F187: x | G187: x | I187: ModernArgentina | J187: x
A188: UPR_1810 | B188: 18100525 | C188: 18110514 | D188: Ar2Bo2ParUru | E188: =VLOOKUP( $A188, Sovereignty!$A$2:$L$510, 12, 0 ) -> x | F188: x | G188: x | I188: RumpArgentina | J188: x
A189: UPR_1776_SPA | B189: 17760801 | C189: 18100525 | D189: Ar2Bo2ParUru | E189: =VLOOKUP( $A189, Sovereignty!$A$2:$L$510, 12, 0 ) -> x | F189: x | G189: x | I189: ModernBolivia | J189: x
A190: PAR_1811 | B190: 18110514 | C190: 20261231 | D190: ModernParaguay | E190: =VLOOKUP( $A190, Sovereignty!$A$2:$L$510, 12, 0 ) -> x | F190: x | G190: x | I190: SeaBolivia | J190: x
A191: ARG_1816 | B191: 18830101 | C191: 20261231 | D191: ModernArgentina | E191: =VLOOKUP( $A191, Sovereignty!$A$2:$L$510, 12, 0 ) -> x | F191: x | G191: x | I191: ModernBrazil | J191: x
A192: ARG_1816 | B192: 18250806 | C192: 18830101 | D192: RumpArgentina | E192: =VLOOKUP( $A192, Sovereignty!$A$2:$L$510, 12, 0 ) -> x | F192: x | G192: x | I192: ColEcuPan | J192: x
A193: ARG_1816 | B193: 18170120 | C193: 18250806 | D193: Ar2Bo2 | E193: =VLOOKUP( $A193, Sovereignty!$A$2:$L$510, 12, 0 ) -> x | F193: x | G193: x | I193: ModernColombia | J193: x
... A207: COL_1819 | B207: 18300503 | C207: 19031106 | D207: ColombiaPanama | E207: =VLOOKUP( $A207, Sovereignty!$A$2:$L$510, 12, 0 ) -> x | F207: x | G207: x | I207: ModernVenezuela | J207: x
A208: COL_1819 | B208: 18300113 | C208: 18300503 | D208: ColEcuPan | E208: =VLOOKUP( $A208, Sovereignty!$A$2:$L$510, 12, 0 ) -> x | F208: x | G208: x
A209: COL_1819 | B209: 18191217 | C209: 18300113 | D209: GranColombia | E209: =VLOOKUP( $A209, Sovereignty!$A$2:$L$510, 12, 0 ) -> x | F209: x | G209: x
A210: COL_1717_SPA | B210: 17170527 | C210: 18191217 | D210: GranColombia | E210: =VLOOKUP( $A210, Sovereignty!$A$2:$L$510, 12, 0 ) -> x | F210: x | G210: x
A211: VEN_1830 | B211: 18300113 | C211: 20261231 | D211: ModernVenezuela | E211: =VLOOKUP( $A211, Sovereignty!$A$2:$L$510, 12, 0 ) -> x | F211: x | G211: x
A212: GUY_1966 | B212: 19660526 | C212: 20261231 | D212: ModernGuyana | E212: =VLOOKUP( $A212, Sovereignty!$A$2:$L$510, 12, 0 ) -> x | F212: x | G212: x
A213: GUI_1831_UK | B213: 18310721 | C213: 19660526 | D213: ModernGuyana | E213: =VLOOKUP( $A213, Sovereignty!$A$2:$L$510, 12, 0 ) -> x | F213: x | G213: x
A214: SUR_1975 | B214: 19751125 | C214: 20261231 | D214: ModernSuriname | E214: =VLOOKUP( $A214, Sovereignty!$A$2:$L$510, 12, 0 ) -> x | F214: x | G214: x
A215: SUR_1954_NET | B215: 19541215 | C215: 19751125 | D215: ModernSuriname | E215: =VLOOKUP( $A215, Sovereignty!$A$2:$L$510, 12, 0 ) -> x | F215: x | G215: x
A216: GUI_1667_NET | B216: 18310721 | C216: 19541215 | D216: ModernSuriname | E216: =VLOOKUP( $A216, Sovereignty!$A$2:$L$510, 12, 0 ) -> x
A217: GUI_1667_NET | B217: 16670731 | C217: 18310721 | D217: SurinameGuyana | E217: =VLOOKUP( $A217, Sovereignty!$A$2:$L$510, 12, 0 ) -> x
A218: FGU_1643_FRA | B218: 16430926 | C218: 20261231 | D218: FrenchGuiana | E218: =VLOOKUP( $A218, Sovereignty!$A$2:$L$510, 12, 0 ) -> x
A219: SGP_1965 | B219: 19650809 | C219: 20261231 | D219: Singapore | E219: =VLOOKUP( $A219, Sovereignty!$A$2:$L$510, 12, 0 ) -> 0
A220: SGP_1963_MLY | B220: 19630831 | C220: 19650809 | D220: Singapore | E220: =VLOOKUP( $A220, Sovereignty!$A$2:$L$510, 12, 0 ) -> 0
A221: SGP_1946_UK | B221: 19460401 | C221: 19630831 | D221: Singapore | E221: =VLOOKUP( $A221, Sovereignty!$A$2:$L$510, 12, 0 ) -> 0
A222: STR_1826_UK | B222: 18260101 | C222: 19460401 | D222: Singapore | E222: =VLOOKUP( $A222, Sovereignty!$A$2:$L$510, 12, 0 ) -> 0
A223: TUR_1922 | B223: 19221101 | C223: 20261231 | D223: Turkey | E223: =VLOOKUP( $A223, Sovereignty!$A$2:$L$510, 12, 0 ) -> 0
A224: OTT_1453 | B224: 14530529 | C224: 19221101 | D224: Turkey | E224: =VLOOKUP( $A224, Sovereignty!$A$2:$L$510, 12, 0 ) -> 0
A225: CYP_1960 | B225: 19600816 | C225: 20261231 | D225: Cyprus | E225: =VLOOKUP( $A225, Sovereignty!$A$2:$L$510, 12, 0 ) -> 0
A226: CYP_1878_UK | B226: 18780604 | C226: 19600816 | D226: Cyprus | E226: =VLOOKUP( $A226, Sovereignty!$A$2:$L$510, 12, 0 ) -> 0
A227: CYP_1571_OTT | B227: 15710801 | C227: 18780604 | D227: Cyprus | E227: =VLOOKUP( $A227, Sovereignty!$A$2:$L$510, 12, 0 ) -> 0
... A546: GUA_1898_US | B546: 18981210 | C546: 20261231 | D546: Guam | E546: =VLOOKUP( $A546, Sovereignty!$A$2:$L$510, 12, 0 ) -> 0
A547: FSM_1986 | B547: 1986 | C547: 20261231 | D547: Micronesia | E547: =VLOOKUP( $A547, Sovereignty!$A$2:$L$510, 12, 0 ) -> 0 | F547: x | G547: x
A548: PAL_1994 | B548: 19941001 | C548: 20261231 | D548: Palau | E548: =VLOOKUP( $A548, Sovereignty!$A$2:$L$510, 12, 0 ) -> 0 | F548: x | G548: x
A549: SEI_1571_SPA | B549: 15710101 | C549: 18981210 | D549: SpanishEastIndies | E549: =VLOOKUP( $A549, Sovereignty!$A$2:$L$510, 12, 0 ) -> 0 | F549: x | G549: x
